{
  "11" : {"lexicalEntry":["oewn-11-s","oewn-11-n"]},
  "105" : {"lexicalEntry":["oewn-105-s"]},
  "A/C" : {"lexicalEntry":["oewn-A-sl-C-n"]},
  "Addison's syndrome" : {"lexicalEntry":["oewn-Addison-ap-s_syndrome-n"]},
  "African elephant" : {"lexicalEntry":["oewn-African_elephant-n"]},
  "Akron" : {"lexicalEntry":["oewn-Akron-n"]},
  "Aleksandr Solzhenitsyn" : {"lexicalEntry":["oewn-Aleksandr_Solzhenitsyn-n"]},
  "Alice Malsenior Walker" : {"lexicalEntry":["oewn-Alice_Malsenior_Walker-n"]},
  "Alosa chrysocloris" : {"lexicalEntry":["oewn-Alosa_chrysocloris-n"]},
  "Amman" : {"lexicalEntry":["oewn-Amman-n"]},
  "Amorpha canescens" : {"lexicalEntry":["oewn-Amorpha_canescens-n"]},
  "Anas" : {"lexicalEntry":["oewn-Anas-n"]},
  "Apocynum" : {"lexicalEntry":["oewn-Apocynum-n"]},
  "Arno" : {"lexicalEntry":["oewn-Arno-n"]},
  "Ascension of the Lord" : {"lexicalEntry":["oewn-Ascension_of_the_Lord-n"]},
  "Aspleniaceae" : {"lexicalEntry":["oewn-Aspleniaceae-n"]},
  "Aureolaria pedicularia" : {"lexicalEntry":["oewn-Aureolaria_pedicularia-n"]},
  "Azolla caroliniana" : {"lexicalEntry":["oewn-Azolla_caroliniana-n"]},
  "Balkan country" : {"lexicalEntry":["oewn-Balkan_country-n"]},
  "Belarus" : {"lexicalEntry":["oewn-Belarus-n"]},
  "Belgian Congo" : {"lexicalEntry":["oewn-Belgian_Congo-n"]},
  "Bengal kino" : {"lexicalEntry":["oewn-Bengal_kino-n"]},
  "Beta vulgaris vulgaris" : {"lexicalEntry":["oewn-Beta_vulgaris_vulgaris-n"]},
  "Bowditch" : {"lexicalEntry":["oewn-Bowditch-n"]},
  "Bunyan" : {"lexicalEntry":["oewn-Bunyan-n"]},
  "Byelorussian language" : {"lexicalEntry":["oewn-Byelorussian_language-n"]},
  "Cajanus cajan" : {"lexicalEntry":["oewn-Cajanus_cajan-n"]},
  "California sagebrush" : {"lexicalEntry":["oewn-California_sagebrush-n"]},
  "Calixtus II" : {"lexicalEntry":["oewn-Calixtus_II-n"]},
  "Castoroides" : {"lexicalEntry":["oewn-Castoroides-n"]},
  "Cathars" : {"lexicalEntry":["oewn-Cathars-n"]},
  "Cellini" : {"lexicalEntry":["oewn-Cellini-n"]},
  "Central Thai" : {"lexicalEntry":["oewn-Central_Thai-n"]},
  "Centropistes striata" : {"lexicalEntry":["oewn-Centropistes_striata-n"]},
  "Chinese celery" : {"lexicalEntry":["oewn-Chinese_celery-n"]},
  "Cimicifuga" : {"lexicalEntry":["oewn-Cimicifuga-n"]},
  "Colorado four o'clock" : {"lexicalEntry":["oewn-Colorado_four_o-ap-clock-n"]},
  "Cyamus" : {"lexicalEntry":["oewn-Cyamus-n"]},
  "David Rittenhouse" : {"lexicalEntry":["oewn-David_Rittenhouse-n"]},
  "Dermatobia" : {"lexicalEntry":["oewn-Dermatobia-n"]},
  "Dmitri Mendeleyev" : {"lexicalEntry":["oewn-Dmitri_Mendeleyev-n"]},
  "Dwight Filley Davis" : {"lexicalEntry":["oewn-Dwight_Filley_Davis-n"]},
  "Einstein" : {"lexicalEntry":["oewn-Einstein-n"]},
  "Elagatis bipinnulata" : {"lexicalEntry":["oewn-Elagatis_bipinnulata-n"]},
  "Emma Hart Willard" : {"lexicalEntry":["oewn-Emma_Hart_Willard-n"]},
  "Enhydra lutris" : {"lexicalEntry":["oewn-Enhydra_lutris-n"]},
  "Epistle of James" : {"lexicalEntry":["oewn-Epistle_of_James-n"]},
  "Ernst Heinrich Haeckel" : {"lexicalEntry":["oewn-Ernst_Heinrich_Haeckel-n"]},
  "Erysimum cheiranthoides" : {"lexicalEntry":["oewn-Erysimum_cheiranthoides-n"]},
  "Eupatorium aya-pana" : {"lexicalEntry":["oewn-Eupatorium_aya-pana-n"]},
  "February" : {"lexicalEntry":["oewn-February-n"]},
  "Francis Albert Sinatra" : {"lexicalEntry":["oewn-Francis_Albert_Sinatra-n"]},
  "Fulbe" : {"lexicalEntry":["oewn-Fulbe-n"]},
  "GHQ" : {"lexicalEntry":["oewn-GHQ-n"]},
  "GST" : {"lexicalEntry":["oewn-GST-n"]},
  "Galahad" : {"lexicalEntry":["oewn-Galahad-n"]},
  "George S. Kaufman" : {"lexicalEntry":["oewn-George_S._Kaufman-n"]},
  "George Vancouver" : {"lexicalEntry":["oewn-George_Vancouver-n"]},
  "Grand Teton National Park" : {"lexicalEntry":["oewn-Grand_Teton_National_Park-n"]},
  "Hazardia" : {"lexicalEntry":["oewn-Hazardia-n"]},
  "Henry VI" : {"lexicalEntry":["oewn-Henry_VI-n"]},
  "Hermann Hesse" : {"lexicalEntry":["oewn-Hermann_Hesse-n"]},
  "Indian mallow" : {"lexicalEntry":["oewn-Indian_mallow-n"]},
  "Irish setter" : {"lexicalEntry":["oewn-Irish_setter-n"]},
  "Jean Arp" : {"lexicalEntry":["oewn-Jean_Arp-n"]},
  "Jean-Paul Marat" : {"lexicalEntry":["oewn-Jean-Paul_Marat-n"]},
  "Josip Broz" : {"lexicalEntry":["oewn-Josip_Broz-n"]},
  "Jotun" : {"lexicalEntry":["oewn-Jotun-n"]},
  "Kirghizstan" : {"lexicalEntry":["oewn-Kirghizstan-n"]},
  "Kurdish language" : {"lexicalEntry":["oewn-Kurdish_language-n"]},
  "Latakia" : {"lexicalEntry":["oewn-Latakia-n"]},
  "Ledbetter" : {"lexicalEntry":["oewn-Ledbetter-n"]},
  "Lentinus" : {"lexicalEntry":["oewn-Lentinus-n"]},
  "Light Within" : {"lexicalEntry":["oewn-Light_Within-n"]},
  "Lithophragma parviflorum" : {"lexicalEntry":["oewn-Lithophragma_parviflorum-n"]},
  "Lobotidae" : {"lexicalEntry":["oewn-Lobotidae-n"]},
  "Loki" : {"lexicalEntry":["oewn-Loki-n"]},
  "Lola Montez" : {"lexicalEntry":["oewn-Lola_Montez-n"]},
  "Louis le Hutin" : {"lexicalEntry":["oewn-Louis_le_Hutin-n"]},
  "Lupinus subcarnosus" : {"lexicalEntry":["oewn-Lupinus_subcarnosus-n"]},
  "MOT test" : {"lexicalEntry":["oewn-MOT_test-n"]},
  "Marxist-Leninist" : {"lexicalEntry":["oewn-Marxist-Leninist-a"]},
  "Mayday" : {"lexicalEntry":["oewn-Mayday-n"]},
  "Mongolic language" : {"lexicalEntry":["oewn-Mongolic_language-n"]},
  "Morgan le Fay" : {"lexicalEntry":["oewn-Morgan_le_Fay-n"]},
  "Mormon" : {"lexicalEntry":["oewn-Mormon-n","oewn-Mormon-a"]},
  "Myrmecobius" : {"lexicalEntry":["oewn-Myrmecobius-n"]},
  "Natrix sipedon" : {"lexicalEntry":["oewn-Natrix_sipedon-n"]},
  "New World monkey" : {"lexicalEntry":["oewn-New_World_monkey-n"]},
  "Newton's theory of gravitation" : {"lexicalEntry":["oewn-Newton-ap-s_theory_of_gravitation-n"]},
  "Niccolo Machiavelli" : {"lexicalEntry":["oewn-Niccolo_Machiavelli-n"]},
  "Nymphaea lotus" : {"lexicalEntry":["oewn-Nymphaea_lotus-n"]},
  "Oujda" : {"lexicalEntry":["oewn-Oujda-n"]},
  "Paiute" : {"lexicalEntry":["oewn-Paiute-n"]},
  "Pan troglodytes troglodytes" : {"lexicalEntry":["oewn-Pan_troglodytes_troglodytes-n"]},
  "Pandion haliaetus" : {"lexicalEntry":["oewn-Pandion_haliaetus-n"]},
  "Persian Gulf" : {"lexicalEntry":["oewn-Persian_Gulf-n"]},
  "Picris echioides" : {"lexicalEntry":["oewn-Picris_echioides-n"]},
  "Plethodon cinereus" : {"lexicalEntry":["oewn-Plethodon_cinereus-n"]},
  "Plymouth Rock" : {"lexicalEntry":["oewn-Plymouth_Rock-n"]},
  "Polynesia" : {"lexicalEntry":["oewn-Polynesia-n"]},
  "Populus nigra italica" : {"lexicalEntry":["oewn-Populus_nigra_italica-n"]},
  "Prince Otto Eduard Leopold von Bismarck" : {"lexicalEntry":["oewn-Prince_Otto_Eduard_Leopold_von_Bismarck-n"]},
  "Principen" : {"lexicalEntry":["oewn-Principen-n"]},
  "Prociphilus tessellatus" : {"lexicalEntry":["oewn-Prociphilus_tessellatus-n"]},
  "Prosopis juliflora" : {"lexicalEntry":["oewn-Prosopis_juliflora-n"]},
  "Pseudoryx" : {"lexicalEntry":["oewn-Pseudoryx-n"]},
  "Pseudotaxus chienii" : {"lexicalEntry":["oewn-Pseudotaxus_chienii-n"]},
  "Pygoscelis adeliae" : {"lexicalEntry":["oewn-Pygoscelis_adeliae-n"]},
  "Quebec City" : {"lexicalEntry":["oewn-Quebec_City-n"]},
  "Raja radiata" : {"lexicalEntry":["oewn-Raja_radiata-n"]},
  "Rebecca" : {"lexicalEntry":["oewn-Rebecca-n"]},
  "Republic of China" : {"lexicalEntry":["oewn-Republic_of_China-n"]},
  "Rickettsiales" : {"lexicalEntry":["oewn-Rickettsiales-n"]},
  "Ringling" : {"lexicalEntry":["oewn-Ringling-n"]},
  "Samoyedic-speaking" : {"lexicalEntry":["oewn-Samoyedic-speaking-s"]},
  "Santa Sofia" : {"lexicalEntry":["oewn-Santa_Sofia-n"]},
  "Sao Thome e Principe monetary unit" : {"lexicalEntry":["oewn-Sao_Thome_e_Principe_monetary_unit-n"]},
  "Saururus" : {"lexicalEntry":["oewn-Saururus-n"]},
  "Seattle Slew" : {"lexicalEntry":["oewn-Seattle_Slew-n"]},
  "Sergei Eisenstein" : {"lexicalEntry":["oewn-Sergei_Eisenstein-n"]},
  "Shiah Islam" : {"lexicalEntry":["oewn-Shiah_Islam-n"]},
  "Sisters of st. Michael the Archangel" : {"lexicalEntry":["oewn-Sisters_of_st._Michael_the_Archangel-n"]},
  "Sofia" : {"lexicalEntry":["oewn-Sofia-n"]},
  "Solidago multiradiata" : {"lexicalEntry":["oewn-Solidago_multiradiata-n"]},
  "Sousse" : {"lexicalEntry":["oewn-Sousse-n"]},
  "South Korean monetary unit" : {"lexicalEntry":["oewn-South_Korean_monetary_unit-n"]},
  "Spergula" : {"lexicalEntry":["oewn-Spergula-n"]},
  "Sudanese pound" : {"lexicalEntry":["oewn-Sudanese_pound-n"]},
  "Sumatran" : {"lexicalEntry":["oewn-Sumatran-n","oewn-Sumatran-a"]},
  "Sverige" : {"lexicalEntry":["oewn-Sverige-n"]},
  "Synanceja" : {"lexicalEntry":["oewn-Synanceja-n"]},
  "Tacca leontopetaloides" : {"lexicalEntry":["oewn-Tacca_leontopetaloides-n"]},
  "Thammuz" : {"lexicalEntry":["oewn-Thammuz-n"]},
  "Thule" : {"lexicalEntry":["oewn-Thule-n"]},
  "Tombigbee River" : {"lexicalEntry":["oewn-Tombigbee_River-n"]},
  "Upper Tunguska" : {"lexicalEntry":["oewn-Upper_Tunguska-n"]},
  "Utug" : {"lexicalEntry":["oewn-Utug-n"]},
  "Veratrum" : {"lexicalEntry":["oewn-Veratrum-n"]},
  "Viminaria denudata" : {"lexicalEntry":["oewn-Viminaria_denudata-n"]},
  "Walter Rudolf Hess" : {"lexicalEntry":["oewn-Walter_Rudolf_Hess-n"]},
  "Wesleyan Methodist Church" : {"lexicalEntry":["oewn-Wesleyan_Methodist_Church-n"]},
  "Westminster Abbey" : {"lexicalEntry":["oewn-Westminster_Abbey-n"]},
  "William Wordsworth" : {"lexicalEntry":["oewn-William_Wordsworth-n"]},
  "Wisteria venusta" : {"lexicalEntry":["oewn-Wisteria_venusta-n"]},
  "Woolley" : {"lexicalEntry":["oewn-Woolley-n"]},
  "Yamamoto" : {"lexicalEntry":["oewn-Yamamoto-n"]},
  "abdominal aorta" : {"lexicalEntry":["oewn-abdominal_aorta-n"]},
  "abdominal cavity" : {"lexicalEntry":["oewn-abdominal_cavity-n"]},
  "absentee ballot" : {"lexicalEntry":["oewn-absentee_ballot-n"]},
  "absolute alcohol" : {"lexicalEntry":["oewn-absolute_alcohol-n"]},
  "absurd" : {"lexicalEntry":["oewn-absurd-s","oewn-absurd-n"]},
  "account statement" : {"lexicalEntry":["oewn-account_statement-n"]},
  "adjuvant" : {"lexicalEntry":["oewn-adjuvant-s","oewn-adjuvant-n"]},
  "advertorial" : {"lexicalEntry":["oewn-advertorial-n"]},
  "allowance" : {"lexicalEntry":["oewn-allowance-n","oewn-allowance-v"]},
  "alluvial soil" : {"lexicalEntry":["oewn-alluvial_soil-n"]},
  "aluminium nitrate" : {"lexicalEntry":["oewn-aluminium_nitrate-n"]},
  "amphibrach" : {"lexicalEntry":["oewn-amphibrach-n"]},
  "anamorphosis" : {"lexicalEntry":["oewn-anamorphosis-n"]},
  "anaphoric pronoun" : {"lexicalEntry":["oewn-anaphoric_pronoun-n"]},
  "angiocardiogram" : {"lexicalEntry":["oewn-angiocardiogram-n"]},
  "animal product" : {"lexicalEntry":["oewn-animal_product-n"]},
  "anisogamic" : {"lexicalEntry":["oewn-anisogamic-a"]},
  "ankyloglossia" : {"lexicalEntry":["oewn-ankyloglossia-n"]},
  "annual salt-marsh aster" : {"lexicalEntry":["oewn-annual_salt-marsh_aster-n"]},
  "antibacterial drug" : {"lexicalEntry":["oewn-antibacterial_drug-n"]},
  "antiestablishmentarianism" : {"lexicalEntry":["oewn-antiestablishmentarianism-n"]},
  "apologist" : {"lexicalEntry":["oewn-apologist-n"]},
  "apparatus urogenitalis" : {"lexicalEntry":["oewn-apparatus_urogenitalis-n"]},
  "applause" : {"lexicalEntry":["oewn-applause-n"]},
  "aqua" : {"lexicalEntry":["oewn-aqua-n"]},
  "archesporium" : {"lexicalEntry":["oewn-archesporium-n"]},
  "armored dinosaur" : {"lexicalEntry":["oewn-armored_dinosaur-n"]},
  "as usual" : {"lexicalEntry":["oewn-as_usual-r"]},
  "attester" : {"lexicalEntry":["oewn-attester-n"]},
  "automobile traffic" : {"lexicalEntry":["oewn-automobile_traffic-n"]},
  "axillary vein" : {"lexicalEntry":["oewn-axillary_vein-n"]},
  "azo group" : {"lexicalEntry":["oewn-azo_group-n"]},
  "ball hawk" : {"lexicalEntry":["oewn-ball_hawk-n"]},
  "bar absolute" : {"lexicalEntry":["oewn-bar_absolute-n"]},
  "baryon number" : {"lexicalEntry":["oewn-baryon_number-n"]},
  "bent-grass" : {"lexicalEntry":["oewn-bent-grass-n"]},
  "bentonite" : {"lexicalEntry":["oewn-bentonite-n"]},
  "beseech" : {"lexicalEntry":["oewn-beseech-v"]},
  "bird of paradise" : {"lexicalEntry":["oewn-bird_of_paradise-n"]},
  "bister" : {"lexicalEntry":["oewn-bister-n"]},
  "blistering agent" : {"lexicalEntry":["oewn-blistering_agent-n"]},
  "block letter" : {"lexicalEntry":["oewn-block_letter-n"]},
  "blood poisoning" : {"lexicalEntry":["oewn-blood_poisoning-n"]},
  "boffo" : {"lexicalEntry":["oewn-boffo-s"]},
  "boom" : {"lexicalEntry":["oewn-boom-n","oewn-boom-v"]},
  "box Kodak" : {"lexicalEntry":["oewn-box_Kodak-n"]},
  "box huckleberry" : {"lexicalEntry":["oewn-box_huckleberry-n"]},
  "bravery" : {"lexicalEntry":["oewn-bravery-n"]},
  "brown cup" : {"lexicalEntry":["oewn-brown_cup-n"]},
  "brownish" : {"lexicalEntry":["oewn-brownish-s"]},
  "burglarise" : {"lexicalEntry":["oewn-burglarise-v"]},
  "callithumpian" : {"lexicalEntry":["oewn-callithumpian-a"]},
  "candela" : {"lexicalEntry":["oewn-candela-n"]},
  "candidate" : {"lexicalEntry":["oewn-candidate-n"]},
  "capita" : {"form":["oewn-caput-n"]},
  "carillon" : {"lexicalEntry":["oewn-carillon-n"]},
  "cartoonist" : {"lexicalEntry":["oewn-cartoonist-n"]},
  "castellated" : {"lexicalEntry":["oewn-castellated-s"]},
  "cathartid" : {"lexicalEntry":["oewn-cathartid-n"]},
  "cattleya" : {"lexicalEntry":["oewn-cattleya-n"]},
  "cavity wall" : {"lexicalEntry":["oewn-cavity_wall-n"]},
  "cellulosid" : {"lexicalEntry":["oewn-cellulosid-a"]},
  "central gyrus" : {"lexicalEntry":["oewn-central_gyrus-n"]},
  "cervical vertebra" : {"lexicalEntry":["oewn-cervical_vertebra-n"]},
  "chamfer" : {"lexicalEntry":["oewn-chamfer-n","oewn-chamfer-v"]},
  "cherrystone clam" : {"lexicalEntry":["oewn-cherrystone_clam-n"]},
  "chronograph" : {"lexicalEntry":["oewn-chronograph-n"]},
  "clinch" : {"lexicalEntry":["oewn-clinch-n","oewn-clinch-v"]},
  "coastguard" : {"lexicalEntry":["oewn-coastguard-n"]},
  "coelenterate family" : {"lexicalEntry":["oewn-coelenterate_family-n"]},
  "collector's item" : {"lexicalEntry":["oewn-collector-ap-s_item-n"]},
  "colonist" : {"lexicalEntry":["oewn-colonist-n"]},
  "compositor" : {"lexicalEntry":["oewn-compositor-n"]},
  "confederate" : {"lexicalEntry":["oewn-confederate-s","oewn-confederate-n","oewn-confederate-v"]},
  "conferment" : {"lexicalEntry":["oewn-conferment-n"]},
  "conjugated" : {"lexicalEntry":["oewn-conjugated-s"]},
  "conjunctiva" : {"lexicalEntry":["oewn-conjunctiva-n"]},
  "conniving" : {"lexicalEntry":["oewn-conniving-s"]},
  "constrained" : {"lexicalEntry":["oewn-constrained-s"]},
  "contact dermatitis" : {"lexicalEntry":["oewn-contact_dermatitis-n"]},
  "contraceptive" : {"lexicalEntry":["oewn-contraceptive-s","oewn-contraceptive-n"]},
  "coral-root bittercress" : {"lexicalEntry":["oewn-coral-root_bittercress-n"]},
  "corn borer moth" : {"lexicalEntry":["oewn-corn_borer_moth-n"]},
  "country borage" : {"lexicalEntry":["oewn-country_borage-n"]},
  "country doctor" : {"lexicalEntry":["oewn-country_doctor-n"]},
  "crackpot" : {"lexicalEntry":["oewn-crackpot-n"]},
  "cretaceous" : {"lexicalEntry":["oewn-cretaceous-a"]},
  "crowbait" : {"lexicalEntry":["oewn-crowbait-n"]},
  "curliness" : {"lexicalEntry":["oewn-curliness-n"]},
  "cutpurse" : {"lexicalEntry":["oewn-cutpurse-n"]},
  "cyanide poisoning" : {"lexicalEntry":["oewn-cyanide_poisoning-n"]},
  "cyberart" : {"lexicalEntry":["oewn-cyberart-n"]},
  "cycad" : {"lexicalEntry":["oewn-cycad-n"]},
  "decoction process" : {"lexicalEntry":["oewn-decoction_process-n"]},
  "decoratively" : {"lexicalEntry":["oewn-decoratively-r"]},
  "deerstalking" : {"lexicalEntry":["oewn-deerstalking-n"]},
  "deglaze" : {"lexicalEntry":["oewn-deglaze-v"]},
  "derision" : {"lexicalEntry":["oewn-derision-n"]},
  "deterred" : {"form":["oewn-deter-v"]},
  "dialyzer" : {"lexicalEntry":["oewn-dialyzer-n"]},
  "dietetical" : {"lexicalEntry":["oewn-dietetical-a"]},
  "diminished arch" : {"lexicalEntry":["oewn-diminished_arch-n"]},
  "disapprovingly" : {"lexicalEntry":["oewn-disapprovingly-r"]},
  "disconcertment" : {"lexicalEntry":["oewn-disconcertment-n"]},
  "disdainfulness" : {"lexicalEntry":["oewn-disdainfulness-n"]},
  "disfavour" : {"lexicalEntry":["oewn-disfavour-n","oewn-disfavour-v"]},
  "dispassionate" : {"lexicalEntry":["oewn-dispassionate-s"]},
  "dollarfishes" : {"form":["oewn-dollarfish-n"]},
  "double-entry bookkeeping" : {"lexicalEntry":["oewn-double-entry_bookkeeping-n"]},
  "drag out" : {"lexicalEntry":["oewn-drag_out-v"]},
  "drogue" : {"lexicalEntry":["oewn-drogue-n"]},
  "duckbilled platypus" : {"lexicalEntry":["oewn-duckbilled_platypus-n"]},
  "dustiness" : {"lexicalEntry":["oewn-dustiness-n"]},
  "earthman" : {"lexicalEntry":["oewn-earthman-n"]},
  "easiness" : {"lexicalEntry":["oewn-easiness-n"]},
  "eavesdrop" : {"lexicalEntry":["oewn-eavesdrop-v"]},
  "ecclesiastical province" : {"lexicalEntry":["oewn-ecclesiastical_province-n"]},
  "eggdrop soup" : {"lexicalEntry":["oewn-eggdrop_soup-n"]},
  "el" : {"lexicalEntry":["oewn-el-n"]},
  "elastic potential energy" : {"lexicalEntry":["oewn-elastic_potential_energy-n"]},
  "electrical circuit" : {"lexicalEntry":["oewn-electrical_circuit-n"]},
  "elicited" : {"lexicalEntry":["oewn-elicited-s"]},
  "emergent evolution" : {"lexicalEntry":["oewn-emergent_evolution-n"]},
  "emu" : {"lexicalEntry":["oewn-emu-n-1","oewn-emu-n-2"]},
  "enantiomorphism" : {"lexicalEntry":["oewn-enantiomorphism-n"]},
  "eoraptor" : {"lexicalEntry":["oewn-eoraptor-n"]},
  "episcleral veins" : {"lexicalEntry":["oewn-episcleral_veins-n"]},
  "esthetics" : {"lexicalEntry":["oewn-esthetics-n"]},
  "evolutionarily" : {"lexicalEntry":["oewn-evolutionarily-r"]},
  "exam" : {"lexicalEntry":["oewn-exam-n"]},
  "exotic" : {"lexicalEntry":["oewn-exotic-s"]},
  "family Ceratodontidae" : {"lexicalEntry":["oewn-family_Ceratodontidae-n"]},
  "family Enterobacteriaceae" : {"lexicalEntry":["oewn-family_Enterobacteriaceae-n"]},
  "family Gadidae" : {"lexicalEntry":["oewn-family_Gadidae-n"]},
  "family Meleagrididae" : {"lexicalEntry":["oewn-family_Meleagrididae-n"]},
  "family Platycephalidae" : {"lexicalEntry":["oewn-family_Platycephalidae-n"]},
  "family Schizaeaceae" : {"lexicalEntry":["oewn-family_Schizaeaceae-n"]},
  "family Stromateidae" : {"lexicalEntry":["oewn-family_Stromateidae-n"]},
  "favourable reception" : {"lexicalEntry":["oewn-favourable_reception-n"]},
  "favourableness" : {"lexicalEntry":["oewn-favourableness-n"]},
  "ferroconcrete" : {"lexicalEntry":["oewn-ferroconcrete-n"]},
  "fibrovascular bundle" : {"lexicalEntry":["oewn-fibrovascular_bundle-n"]},
  "file name" : {"lexicalEntry":["oewn-file_name-n"]},
  "fire bell" : {"lexicalEntry":["oewn-fire_bell-n"]},
  "fire department" : {"lexicalEntry":["oewn-fire_department-n"]},
  "fishery" : {"lexicalEntry":["oewn-fishery-n"]},
  "flaccidity" : {"lexicalEntry":["oewn-flaccidity-n"]},
  "flinthead" : {"lexicalEntry":["oewn-flinthead-n"]},
  "flood tide" : {"lexicalEntry":["oewn-flood_tide-n"]},
  "flophouse" : {"lexicalEntry":["oewn-flophouse-n"]},
  "flyer" : {"lexicalEntry":["oewn-flyer-n"]},
  "fold up" : {"lexicalEntry":["oewn-fold_up-v"]},
  "foreshown" : {"form":["oewn-foreshow-v"]},
  "freetailed bat" : {"lexicalEntry":["oewn-freetailed_bat-n"]},
  "frequency modulation" : {"lexicalEntry":["oewn-frequency_modulation-n"]},
  "frill" : {"lexicalEntry":["oewn-frill-n"]},
  "fulcra" : {"form":["oewn-fulcrum-n"]},
  "gaping" : {"lexicalEntry":["oewn-gaping-s"]},
  "gardener's delight" : {"lexicalEntry":["oewn-gardener-ap-s_delight-n"]},
  "geneva" : {"lexicalEntry":["oewn-geneva-n"]},
  "genitalia" : {"lexicalEntry":["oewn-genitalia-n"]},
  "genus Bubo" : {"lexicalEntry":["oewn-genus_Bubo-n"]},
  "genus Centropristis" : {"lexicalEntry":["oewn-genus_Centropristis-n"]},
  "genus Cliftonia" : {"lexicalEntry":["oewn-genus_Cliftonia-n"]},
  "genus Comatula" : {"lexicalEntry":["oewn-genus_Comatula-n"]},
  "genus Edaphosaurus" : {"lexicalEntry":["oewn-genus_Edaphosaurus-n"]},
  "genus Erythrocebus" : {"lexicalEntry":["oewn-genus_Erythrocebus-n"]},
  "genus Gladiolus" : {"lexicalEntry":["oewn-genus_Gladiolus-n"]},
  "genus Jaculus" : {"lexicalEntry":["oewn-genus_Jaculus-n"]},
  "genus Lewisia" : {"lexicalEntry":["oewn-genus_Lewisia-n"]},
  "genus Macronectes" : {"lexicalEntry":["oewn-genus_Macronectes-n"]},
  "genus Naias" : {"lexicalEntry":["oewn-genus_Naias-n"]},
  "genus Nolina" : {"lexicalEntry":["oewn-genus_Nolina-n"]},
  "genus Nomia" : {"lexicalEntry":["oewn-genus_Nomia-n"]},
  "genus Periophthalmus" : {"lexicalEntry":["oewn-genus_Periophthalmus-n"]},
  "genus Roridula" : {"lexicalEntry":["oewn-genus_Roridula-n"]},
  "genus Saccharum" : {"lexicalEntry":["oewn-genus_Saccharum-n"]},
  "genus Vanda" : {"lexicalEntry":["oewn-genus_Vanda-n"]},
  "genus Wynnea" : {"lexicalEntry":["oewn-genus_Wynnea-n"]},
  "geometric" : {"lexicalEntry":["oewn-geometric-s","oewn-geometric-a"]},
  "gerrymander" : {"lexicalEntry":["oewn-gerrymander-n","oewn-gerrymander-v"]},
  "ghoul" : {"lexicalEntry":["oewn-ghoul-n"]},
  "glad hand" : {"lexicalEntry":["oewn-glad_hand-n"]},
  "golden-brown" : {"lexicalEntry":["oewn-golden-brown-s"]},
  "gonadotrophic hormone" : {"lexicalEntry":["oewn-gonadotrophic_hormone-n"]},
  "gorgonian" : {"lexicalEntry":["oewn-gorgonian-n"]},
  "grapefruit" : {"lexicalEntry":["oewn-grapefruit-n"]},
  "graphology" : {"lexicalEntry":["oewn-graphology-n"]},
  "guarantee" : {"lexicalEntry":["oewn-guarantee-n","oewn-guarantee-v"]},
  "guitar-shaped" : {"lexicalEntry":["oewn-guitar-shaped-s"]},
  "gunfire" : {"lexicalEntry":["oewn-gunfire-n"]},
  "guttural consonant" : {"lexicalEntry":["oewn-guttural_consonant-n"]},
  "gynobase" : {"lexicalEntry":["oewn-gynobase-n"]},
  "hammock" : {"lexicalEntry":["oewn-hammock-n"]},
  "handbow" : {"lexicalEntry":["oewn-handbow-n"]},
  "hardened" : {"lexicalEntry":["oewn-hardened-a","oewn-hardened-s"]},
  "head shop" : {"lexicalEntry":["oewn-head_shop-n"]},
  "headscarf" : {"lexicalEntry":["oewn-headscarf-n"]},
  "help" : {"lexicalEntry":["oewn-help-n","oewn-help-v"]},
  "hermetically" : {"lexicalEntry":["oewn-hermetically-r"]},
  "herrerasaur" : {"lexicalEntry":["oewn-herrerasaur-n"]},
  "hexanedioic acid" : {"lexicalEntry":["oewn-hexanedioic_acid-n"]},
  "high stepper" : {"lexicalEntry":["oewn-high_stepper-n"]},
  "hippest" : {"form":["oewn-hip-s"]},
  "hit the hay" : {"lexicalEntry":["oewn-hit_the_hay-v"]},
  "honesty" : {"lexicalEntry":["oewn-honesty-n"]},
  "hot-work steel" : {"lexicalEntry":["oewn-hot-work_steel-n"]},
  "hurricane lamp" : {"lexicalEntry":["oewn-hurricane_lamp-n"]},
  "hyponatremia" : {"lexicalEntry":["oewn-hyponatremia-n"]},
  "in due season" : {"lexicalEntry":["oewn-in_due_season-r"]},
  "inapplicability" : {"lexicalEntry":["oewn-inapplicability-n"]},
  "induction" : {"lexicalEntry":["oewn-induction-n"]},
  "industrialist" : {"lexicalEntry":["oewn-industrialist-n"]},
  "inefficacy" : {"lexicalEntry":["oewn-inefficacy-n"]},
  "inscribed" : {"lexicalEntry":["oewn-inscribed-s"]},
  "insightful" : {"lexicalEntry":["oewn-insightful-s"]},
  "instruction manual" : {"lexicalEntry":["oewn-instruction_manual-n"]},
  "insurance policy" : {"lexicalEntry":["oewn-insurance_policy-n"]},
  "interact" : {"lexicalEntry":["oewn-interact-v"]},
  "intercalate" : {"lexicalEntry":["oewn-intercalate-v"]},
  "interquartile range" : {"lexicalEntry":["oewn-interquartile_range-n"]},
  "intimately" : {"lexicalEntry":["oewn-intimately-r"]},
  "intrench" : {"lexicalEntry":["oewn-intrench-v"]},
  "invariably" : {"lexicalEntry":["oewn-invariably-r"]},
  "iodide" : {"lexicalEntry":["oewn-iodide-n"]},
  "irrepressible" : {"lexicalEntry":["oewn-irrepressible-s"]},
  "irresponsibility" : {"lexicalEntry":["oewn-irresponsibility-n"]},
  "ischemic anoxia" : {"lexicalEntry":["oewn-ischemic_anoxia-n"]},
  "jabbering" : {"lexicalEntry":["oewn-jabbering-n"]},
  "jackdaw" : {"lexicalEntry":["oewn-jackdaw-n"]},
  "jazz festival" : {"lexicalEntry":["oewn-jazz_festival-n"]},
  "jewelled headdress" : {"lexicalEntry":["oewn-jewelled_headdress-n"]},
  "jingoistic" : {"lexicalEntry":["oewn-jingoistic-s"]},
  "kerb crawler" : {"lexicalEntry":["oewn-kerb_crawler-n"]},
  "klavern" : {"lexicalEntry":["oewn-klavern-n"]},
  "knocker" : {"lexicalEntry":["oewn-knocker-n"]},
  "knowledgeable" : {"lexicalEntry":["oewn-knowledgeable-s"]},
  "laden" : {"lexicalEntry":["oewn-laden-s","oewn-laden-v"],"form":["oewn-lade-v"]},
  "laicise" : {"lexicalEntry":["oewn-laicise-v"]},
  "lanceolate" : {"lexicalEntry":["oewn-lanceolate-s"]},
  "landing net" : {"lexicalEntry":["oewn-landing_net-n"]},
  "lapsing" : {"lexicalEntry":["oewn-lapsing-n"]},
  "late blight" : {"lexicalEntry":["oewn-late_blight-n"]},
  "letdown" : {"lexicalEntry":["oewn-letdown-n"]},
  "liberalise" : {"lexicalEntry":["oewn-liberalise-v"]},
  "liliopsid family" : {"lexicalEntry":["oewn-liliopsid_family-n"]},
  "longanimous" : {"lexicalEntry":["oewn-longanimous-s"]},
  "looseness of the bowels" : {"lexicalEntry":["oewn-looseness_of_the_bowels-n"]},
  "lulu" : {"lexicalEntry":["oewn-lulu-n"]},
  "lunar crater" : {"lexicalEntry":["oewn-lunar_crater-n"]},
  "machine screw" : {"lexicalEntry":["oewn-machine_screw-n"]},
  "magnetics" : {"lexicalEntry":["oewn-magnetics-n"]},
  "making" : {"lexicalEntry":["oewn-making-n"]},
  "manoeuver" : {"lexicalEntry":["oewn-manoeuver-v"]},
  "marsh hare" : {"lexicalEntry":["oewn-marsh_hare-n"]},
  "mass-produce" : {"lexicalEntry":["oewn-mass-produce-v"]},
  "mat up" : {"lexicalEntry":["oewn-mat_up-v"]},
  "matriarchic" : {"lexicalEntry":["oewn-matriarchic-s"]},
  "maximum" : {"lexicalEntry":["oewn-maximum-a","oewn-maximum-n"]},
  "measuring block" : {"lexicalEntry":["oewn-measuring_block-n"]},
  "measuring instrument" : {"lexicalEntry":["oewn-measuring_instrument-n"]},
  "medico" : {"lexicalEntry":["oewn-medico-n"]},
  "melting point" : {"lexicalEntry":["oewn-melting_point-n"]},
  "mental deficiency" : {"lexicalEntry":["oewn-mental_deficiency-n"]},
  "mentalism" : {"lexicalEntry":["oewn-mentalism-n"]},
  "meprobamate" : {"lexicalEntry":["oewn-meprobamate-n"]},
  "merge" : {"lexicalEntry":["oewn-merge-v"]},
  "merging" : {"lexicalEntry":["oewn-merging-s","oewn-merging-n"]},
  "military band" : {"lexicalEntry":["oewn-military_band-n"]},
  "militia" : {"lexicalEntry":["oewn-militia-n"]},
  "mind-boggling" : {"lexicalEntry":["oewn-mind-boggling-s"]},
  "misperceive" : {"lexicalEntry":["oewn-misperceive-v"]},
  "mono" : {"lexicalEntry":["oewn-mono-s","oewn-mono-n"]},
  "monocotyledonous" : {"lexicalEntry":["oewn-monocotyledonous-a"]},
  "monocytic leukaemia" : {"lexicalEntry":["oewn-monocytic_leukaemia-n"]},
  "mother-of-pearl cloud" : {"lexicalEntry":["oewn-mother-of-pearl_cloud-n"]},
  "mouton" : {"lexicalEntry":["oewn-mouton-n"]},
  "movie maker" : {"lexicalEntry":["oewn-movie_maker-n"]},
  "muezzin" : {"lexicalEntry":["oewn-muezzin-n"]},
  "multivalence" : {"lexicalEntry":["oewn-multivalence-n"]},
  "myopathy" : {"lexicalEntry":["oewn-myopathy-n"]},
  "nanotechnology" : {"lexicalEntry":["oewn-nanotechnology-n"]},
  "national leader" : {"lexicalEntry":["oewn-national_leader-n"]},
  "natural resources" : {"lexicalEntry":["oewn-natural_resources-n"]},
  "nervus accessorius" : {"lexicalEntry":["oewn-nervus_accessorius-n"]},
  "neuralgy" : {"lexicalEntry":["oewn-neuralgy-n"]},
  "neurohypophysis" : {"lexicalEntry":["oewn-neurohypophysis-n"]},
  "nonadjacent" : {"lexicalEntry":["oewn-nonadjacent-s"]},
  "normalcy" : {"lexicalEntry":["oewn-normalcy-n"]},
  "novillero" : {"lexicalEntry":["oewn-novillero-n"]},
  "nuclear fusion" : {"lexicalEntry":["oewn-nuclear_fusion-n"]},
  "occupational disease" : {"lexicalEntry":["oewn-occupational_disease-n"]},
  "oil refinery" : {"lexicalEntry":["oewn-oil_refinery-n"]},
  "oil shale" : {"lexicalEntry":["oewn-oil_shale-n"]},
  "oil stain" : {"lexicalEntry":["oewn-oil_stain-n"]},
  "oilman" : {"lexicalEntry":["oewn-oilman-n"]},
  "on the fence" : {"lexicalEntry":["oewn-on_the_fence-s"]},
  "one-sided" : {"lexicalEntry":["oewn-one-sided-s","oewn-one-sided-a"]},
  "onomatopoeia" : {"lexicalEntry":["oewn-onomatopoeia-n"]},
  "opportunity cost" : {"lexicalEntry":["oewn-opportunity_cost-n"]},
  "orangutan" : {"lexicalEntry":["oewn-orangutan-n"]},
  "ordinary life insurance" : {"lexicalEntry":["oewn-ordinary_life_insurance-n"]},
  "outer rason" : {"lexicalEntry":["oewn-outer_rason-n"]},
  "overlooked" : {"lexicalEntry":["oewn-overlooked-s"]},
  "overspent" : {"form":["oewn-overspend-v"]},
  "oxidiser" : {"lexicalEntry":["oewn-oxidiser-n"]},
  "oxidoreductase" : {"lexicalEntry":["oewn-oxidoreductase-n"]},
  "pacifically" : {"lexicalEntry":["oewn-pacifically-r"]},
  "paddle-wheeler" : {"lexicalEntry":["oewn-paddle-wheeler-n"]},
  "palmately-lobed" : {"lexicalEntry":["oewn-palmately-lobed-s"]},
  "palpebra" : {"lexicalEntry":["oewn-palpebra-n"]},
  "parachuter" : {"lexicalEntry":["oewn-parachuter-n"]},
  "patchwork quilt" : {"lexicalEntry":["oewn-patchwork_quilt-n"]},
  "pediculosis" : {"lexicalEntry":["oewn-pediculosis-n"]},
  "pelican crossing" : {"lexicalEntry":["oewn-pelican_crossing-n"]},
  "pentail" : {"lexicalEntry":["oewn-pentail-n"]},
  "pentode" : {"lexicalEntry":["oewn-pentode-n"]},
  "peplum" : {"lexicalEntry":["oewn-peplum-n"]},
  "perinatal" : {"lexicalEntry":["oewn-perinatal-a"]},
  "phalangitis" : {"lexicalEntry":["oewn-phalangitis-n"]},
  "philosopher" : {"lexicalEntry":["oewn-philosopher-n"]},
  "phone company" : {"lexicalEntry":["oewn-phone_company-n"]},
  "physic" : {"lexicalEntry":["oewn-physic-n"]},
  "physician" : {"lexicalEntry":["oewn-physician-n"]},
  "pitchier" : {"form":["oewn-pitchy-s"]},
  "political platform" : {"lexicalEntry":["oewn-political_platform-n"]},
  "poop out" : {"lexicalEntry":["oewn-poop_out-v"]},
  "popular front" : {"lexicalEntry":["oewn-popular_front-n"]},
  "pound up" : {"lexicalEntry":["oewn-pound_up-v"]},
  "powerhouse" : {"lexicalEntry":["oewn-powerhouse-n"]},
  "prairie wagon" : {"lexicalEntry":["oewn-prairie_wagon-n"]},
  "pro forma" : {"lexicalEntry":["oewn-pro_forma-s","oewn-pro_forma-r"]},
  "prosthetics" : {"lexicalEntry":["oewn-prosthetics-n"]},
  "pule" : {"lexicalEntry":["oewn-pule-v"]},
  "pup tent" : {"lexicalEntry":["oewn-pup_tent-n"]},
  "purpose-built" : {"lexicalEntry":["oewn-purpose-built-s"]},
  "purveyance" : {"lexicalEntry":["oewn-purveyance-n"]},
  "putty knife" : {"lexicalEntry":["oewn-putty_knife-n"]},
  "pyroelectrical" : {"lexicalEntry":["oewn-pyroelectrical-a"]},
  "queenlike" : {"lexicalEntry":["oewn-queenlike-s"]},
  "quick time" : {"lexicalEntry":["oewn-quick_time-n"]},
  "raiser" : {"lexicalEntry":["oewn-raiser-n"]},
  "raj" : {"lexicalEntry":["oewn-raj-n"]},
  "rank" : {"lexicalEntry":["oewn-rank-s","oewn-rank-v","oewn-rank-n"]},
  "red-lavender" : {"lexicalEntry":["oewn-red-lavender-s"]},
  "refreshment" : {"lexicalEntry":["oewn-refreshment-n"]},
  "represser" : {"lexicalEntry":["oewn-represser-n"]},
  "respectful" : {"lexicalEntry":["oewn-respectful-s","oewn-respectful-a"]},
  "rest" : {"lexicalEntry":["oewn-rest-n","oewn-rest-v"]},
  "rhapsodize" : {"lexicalEntry":["oewn-rhapsodize-v"]},
  "rightist" : {"lexicalEntry":["oewn-rightist-s","oewn-rightist-n"]},
  "roofless" : {"lexicalEntry":["oewn-roofless-a","oewn-roofless-s"]},
  "rope bridge" : {"lexicalEntry":["oewn-rope_bridge-n"]},
  "rose-cheeked" : {"lexicalEntry":["oewn-rose-cheeked-s"]},
  "salability" : {"lexicalEntry":["oewn-salability-n"]},
  "samba" : {"lexicalEntry":["oewn-samba-n","oewn-samba-v"]},
  "schoolchild" : {"lexicalEntry":["oewn-schoolchild-n"]},
  "scimitar" : {"lexicalEntry":["oewn-scimitar-n"]},
  "scow" : {"lexicalEntry":["oewn-scow-n"]},
  "scuffle" : {"lexicalEntry":["oewn-scuffle-n","oewn-scuffle-v"]},
  "scyphozoa" : {"form":["oewn-scyphozoan-n"]},
  "sea swallow" : {"lexicalEntry":["oewn-sea_swallow-n"]},
  "seismal" : {"lexicalEntry":["oewn-seismal-s"]},
  "sericultural" : {"lexicalEntry":["oewn-sericultural-a"]},
  "sexton" : {"lexicalEntry":["oewn-sexton-n"]},
  "shell stitch" : {"lexicalEntry":["oewn-shell_stitch-n","oewn-shell_stitch-v"]},
  "shielded" : {"lexicalEntry":["oewn-shielded-s"]},
  "short-change" : {"lexicalEntry":["oewn-short-change-v"]},
  "short-order" : {"lexicalEntry":["oewn-short-order-a"]},
  "short-toed eagle" : {"lexicalEntry":["oewn-short-toed_eagle-n"]},
  "shower glove" : {"lexicalEntry":["oewn-shower_glove-n"]},
  "shyster" : {"lexicalEntry":["oewn-shyster-n"]},
  "simple mastectomy" : {"lexicalEntry":["oewn-simple_mastectomy-n"]},
  "simple regression" : {"lexicalEntry":["oewn-simple_regression-n"]},
  "singular" : {"lexicalEntry":["oewn-singular-a","oewn-singular-s","oewn-singular-n"]},
  "sinoper" : {"lexicalEntry":["oewn-sinoper-n"]},
  "sissoo" : {"lexicalEntry":["oewn-sissoo-n"]},
  "skintight" : {"lexicalEntry":["oewn-skintight-s"]},
  "sleeplessly" : {"lexicalEntry":["oewn-sleeplessly-r"]},
  "smarmily" : {"lexicalEntry":["oewn-smarmily-r"]},
  "smoking room" : {"lexicalEntry":["oewn-smoking_room-n"]},
  "smooth-shelled" : {"lexicalEntry":["oewn-smooth-shelled-s"]},
  "snowboarding" : {"lexicalEntry":["oewn-snowboarding-n"]},
  "sodalist" : {"lexicalEntry":["oewn-sodalist-n"]},
  "soldierlike" : {"lexicalEntry":["oewn-soldierlike-s"]},
  "sorb apple tree" : {"lexicalEntry":["oewn-sorb_apple_tree-n"]},
  "spatula" : {"lexicalEntry":["oewn-spatula-n"]},
  "speck" : {"lexicalEntry":["oewn-speck-n","oewn-speck-v"]},
  "sport car" : {"lexicalEntry":["oewn-sport_car-n"]},
  "squally" : {"lexicalEntry":["oewn-squally-s"]},
  "standardised" : {"lexicalEntry":["oewn-standardised-s"]},
  "staring" : {"lexicalEntry":["oewn-staring-s"]},
  "startled" : {"lexicalEntry":["oewn-startled-s"]},
  "strong point" : {"lexicalEntry":["oewn-strong_point-n"]},
  "sub-assembly" : {"lexicalEntry":["oewn-sub-assembly-n"]},
  "subfamily Papilionoideae" : {"lexicalEntry":["oewn-subfamily_Papilionoideae-n"]},
  "subgenus Azalea" : {"lexicalEntry":["oewn-subgenus_Azalea-n"]},
  "subordinateness" : {"lexicalEntry":["oewn-subordinateness-n"]},
  "sudden infant death syndrome" : {"lexicalEntry":["oewn-sudden_infant_death_syndrome-n"]},
  "sunsuit" : {"lexicalEntry":["oewn-sunsuit-n"]},
  "support vector network" : {"lexicalEntry":["oewn-support_vector_network-n"]},
  "surgical operation" : {"lexicalEntry":["oewn-surgical_operation-n"]},
  "surmounter" : {"lexicalEntry":["oewn-surmounter-n"]},
  "suspensor" : {"lexicalEntry":["oewn-suspensor-n"]},
  "swiz" : {"lexicalEntry":["oewn-swiz-n"]},
  "symbolically" : {"lexicalEntry":["oewn-symbolically-r"]},
  "synecdochic" : {"lexicalEntry":["oewn-synecdochic-s"]},
  "taconite" : {"lexicalEntry":["oewn-taconite-n"]},
  "tarring" : {"form":["oewn-tar-v"]},
  "tautness" : {"lexicalEntry":["oewn-tautness-n"]},
  "tawny-brown" : {"lexicalEntry":["oewn-tawny-brown-s"]},
  "tax assessment" : {"lexicalEntry":["oewn-tax_assessment-n"]},
  "taxies" : {"form":["oewn-taxi-n"]},
  "telekinesis" : {"lexicalEntry":["oewn-telekinesis-n"]},
  "terabit" : {"lexicalEntry":["oewn-terabit-n"]},
  "thanksgiving" : {"lexicalEntry":["oewn-thanksgiving-n"]},
  "the Nazarene" : {"lexicalEntry":["oewn-the_Nazarene-n"]},
  "theatregoer" : {"lexicalEntry":["oewn-theatregoer-n"]},
  "theocracy" : {"lexicalEntry":["oewn-theocracy-n"]},
  "thrombus" : {"lexicalEntry":["oewn-thrombus-n"]},
  "throwster" : {"lexicalEntry":["oewn-throwster-n"]},
  "thrust fault" : {"lexicalEntry":["oewn-thrust_fault-n"]},
  "thundershower" : {"lexicalEntry":["oewn-thundershower-n"]},
  "tilt" : {"lexicalEntry":["oewn-tilt-n","oewn-tilt-v"]},
  "titled" : {"lexicalEntry":["oewn-titled-s"]},
  "toe toe" : {"lexicalEntry":["oewn-toe_toe-n"]},
  "tolerable" : {"lexicalEntry":["oewn-tolerable-s","oewn-tolerable-a"]},
  "tracing paper" : {"lexicalEntry":["oewn-tracing_paper-n"]},
  "trade acceptance" : {"lexicalEntry":["oewn-trade_acceptance-n"]},
  "trade wind" : {"lexicalEntry":["oewn-trade_wind-n"]},
  "travel-worn" : {"lexicalEntry":["oewn-travel-worn-s"]},
  "tri-chad" : {"lexicalEntry":["oewn-tri-chad-n"]},
  "triclinium" : {"lexicalEntry":["oewn-triclinium-n"]},
  "trouncing" : {"lexicalEntry":["oewn-trouncing-n"]},
  "turves" : {"form":["oewn-turf-n"]},
  "tyramine" : {"lexicalEntry":["oewn-tyramine-n"]},
  "ulcerous" : {"lexicalEntry":["oewn-ulcerous-s"]},
  "unburden" : {"lexicalEntry":["oewn-unburden-v"]},
  "unconformable" : {"lexicalEntry":["oewn-unconformable-s"]},
  "unconnected" : {"lexicalEntry":["oewn-unconnected-a","oewn-unconnected-s"]},
  "uncritical" : {"lexicalEntry":["oewn-uncritical-a"]},
  "unemotionally" : {"lexicalEntry":["oewn-unemotionally-r"]},
  "unfavorable judgment" : {"lexicalEntry":["oewn-unfavorable_judgment-n"]},
  "ungentlemanly" : {"lexicalEntry":["oewn-ungentlemanly-s"]},
  "unhopeful" : {"lexicalEntry":["oewn-unhopeful-s"]},
  "unkemptness" : {"lexicalEntry":["oewn-unkemptness-n"]},
  "unpopularity" : {"lexicalEntry":["oewn-unpopularity-n"]},
  "unshielded" : {"lexicalEntry":["oewn-unshielded-s"]},
  "unweary" : {"lexicalEntry":["oewn-unweary-s"]},
  "upwards" : {"lexicalEntry":["oewn-upwards-r"]},
  "vaisya" : {"lexicalEntry":["oewn-vaisya-n"]},
  "vela" : {"form":["oewn-velum-n"]},
  "vena vertebralis accessoria" : {"lexicalEntry":["oewn-vena_vertebralis_accessoria-n"]},
  "verger" : {"lexicalEntry":["oewn-verger-n"]},
  "vestibular fold" : {"lexicalEntry":["oewn-vestibular_fold-n"]},
  "victimiser" : {"lexicalEntry":["oewn-victimiser-n"]},
  "volary" : {"lexicalEntry":["oewn-volary-n"]},
  "washing-up" : {"lexicalEntry":["oewn-washing-up-n"]},
  "water-soluble" : {"lexicalEntry":["oewn-water-soluble-s"]},
  "wax-chandler" : {"lexicalEntry":["oewn-wax-chandler-n"]},
  "well-timed" : {"lexicalEntry":["oewn-well-timed-s","oewn-well-timed-r"]},
  "windiness" : {"lexicalEntry":["oewn-windiness-n"]},
  "yieldingly" : {"lexicalEntry":["oewn-yieldingly-r"]},
  "youth movement" : {"lexicalEntry":["oewn-youth_movement-n"]}
}