{
  "oewn-09485903-n" : {"lexicalEntry":["oewn-trough-n"]},
  "oewn-05081057-n" : {"lexicalEntry":["oewn-eccentricity-n"]},
  "oewn-06852240-n" : {"lexicalEntry":["oewn-space-n","oewn-blank-n"]},
  "oewn-02466854-n" : {"lexicalEntry":["oewn-flank-n"]},
  "oewn-07671114-n" : {"lexicalEntry":["oewn-leg-n"]},
  "oewn-14110803-n" : {"lexicalEntry":["oewn-protuberance-n"]},
  "oewn-03658258-n" : {"lexicalEntry":["oewn-lead-n-1","oewn-leash-n","oewn-tether-n"]},
  "oewn-00795757-s" : {"lexicalEntry":["oewn-preponderant-s","oewn-predominant-s","oewn-predominate-s","oewn-paramount-s","oewn-preponderating-s","oewn-overriding-s"]},
  "oewn-01899577-s" : {"lexicalEntry":["oewn-meek-s","oewn-modest-s","oewn-mild-s"]},
  "oewn-00391691-s" : {"lexicalEntry":["oewn-olive-grey-s","oewn-olive-gray-s"]},
  "oewn-00949488-s" : {"lexicalEntry":["oewn-digitate-s","oewn-fingerlike-s"]},
  "oewn-00427844-a" : {"lexicalEntry":["oewn-uncontaminating-a","oewn-clean-a"]},
  "oewn-02388023-s" : {"lexicalEntry":["oewn-synchronised-s","oewn-synchronized-s"]},
  "oewn-00692950-a" : {"lexicalEntry":["oewn-deductible-a"]},
  "oewn-00861240-s" : {"lexicalEntry":["oewn-philosophic-s","oewn-philosophical-s"]},
  "oewn-00873789-s" : {"lexicalEntry":["oewn-unencumbered-s"]},
  "oewn-00505894-a" : {"lexicalEntry":["oewn-comparable-a"]},
  "oewn-00243558-a" : {"lexicalEntry":["oewn-black-a"]},
  "oewn-00934006-s" : {"lexicalEntry":["oewn-out_of_the_blue-s","oewn-unforeseen-s","oewn-unseen-s","oewn-unlooked-for-s","oewn-unanticipated-s"]},
  "oewn-01035369-s" : {"lexicalEntry":["oewn-web-toed-s","oewn-web-footed-s"]},
  "oewn-00407820-s" : {"lexicalEntry":["oewn-white-s","oewn-whitened-s"]},
  "oewn-00662902-a" : {"lexicalEntry":["oewn-one-dimensional-a","oewn-unidimensional-a"]},
  "oewn-01172738-a" : {"lexicalEntry":["oewn-operative-a","oewn-surgical-a"]},
  "oewn-01959465-s" : {"lexicalEntry":["oewn-rude-s","oewn-raw-s","oewn-natural-s"]},
  "oewn-00986145-s" : {"lexicalEntry":["oewn-andante-s"]},
  "oewn-00393428-s" : {"lexicalEntry":["oewn-white-flowered-s"]},
  "oewn-00865005-s" : {"lexicalEntry":["oewn-speculative-s","oewn-notional-s"]},
  "oewn-02269929-s" : {"lexicalEntry":["oewn-liquefied-s","oewn-liquified-s"]},
  "oewn-01414776-s" : {"lexicalEntry":["oewn-apt-s","oewn-liable-s"]},
  "oewn-02281838-s" : {"lexicalEntry":["oewn-stable-s"]},
  "oewn-01632592-s" : {"lexicalEntry":["oewn-abusive-s","oewn-scurrilous-s","oewn-opprobrious-s"]},
  "oewn-01359131-a" : {"lexicalEntry":["oewn-confined-a"]},
  "oewn-02588473-s" : {"lexicalEntry":["oewn-mundane-s","oewn-terrestrial-s"]},
  "oewn-01854629-s" : {"lexicalEntry":["oewn-flamboyant-s","oewn-showy-s","oewn-splashy-s"]},
  "oewn-01193711-s" : {"lexicalEntry":["oewn-weighty-s"]},
  "oewn-00193838-s" : {"lexicalEntry":["oewn-out_of_it-s"]},
  "oewn-01656475-a" : {"lexicalEntry":["oewn-onside-a"]},
  "oewn-02266116-s" : {"lexicalEntry":["oewn-social-s"]},
  "oewn-00890764-s" : {"lexicalEntry":["oewn-halfhearted-s","oewn-tepid-s","oewn-half-hearted-s","oewn-lukewarm-s"]},
  "oewn-01059785-s" : {"lexicalEntry":["oewn-candy-scented-s"]},
  "oewn-00098759-s" : {"lexicalEntry":["oewn-murdered-s"]},
  "oewn-01273285-a" : {"lexicalEntry":["oewn-hurried-a"]},
  "oewn-01050693-s" : {"lexicalEntry":["oewn-subliterary-s"]},
  "oewn-00998815-a" : {"lexicalEntry":["oewn-unfavourable-a","oewn-unfavorable-a"]},
  "oewn-00354202-s" : {"lexicalEntry":["oewn-revised-s"]},
  "oewn-00391905-s" : {"lexicalEntry":["oewn-pearl_grey-s","oewn-pearl_gray-s"]},
  "oewn-02512179-a" : {"lexicalEntry":["oewn-worthless-a"]},
  "oewn-02245505-s" : {"lexicalEntry":["oewn-glassy-s"]},
  "oewn-01522378-s" : {"lexicalEntry":["oewn-noncombatant-s"]},
  "oewn-00158346-s" : {"lexicalEntry":["oewn-nonassertive-s"]},
  "oewn-01882769-s" : {"lexicalEntry":["oewn-modernized-s","oewn-modernised-s"]},
  "oewn-00385257-s" : {"lexicalEntry":["oewn-stone-s"]},
  "oewn-01480698-s" : {"lexicalEntry":["oewn-phallic-s","oewn-priapic-s"]},
  "oewn-00216936-s" : {"lexicalEntry":["oewn-shock-headed-s"]},
  "oewn-01835553-s" : {"lexicalEntry":["oewn-high-voltage-s","oewn-high-potential-s"]},
  "oewn-01004011-s" : {"lexicalEntry":["oewn-well-turned-s"]},
  "oewn-01463188-s" : {"lexicalEntry":["oewn-cuddly-s","oewn-cuddlesome-s"]},
  "oewn-00839043-s" : {"lexicalEntry":["oewn-rough-and-ready-s"]},
  "oewn-02630967-a" : {"lexicalEntry":["oewn-analytic-a"]},
  "oewn-00710244-s" : {"lexicalEntry":["oewn-light-handed-s"]},
  "oewn-01441727-s" : {"lexicalEntry":["oewn-bimestrial-s"]},
  "oewn-00941479-s" : {"lexicalEntry":["oewn-invalid-s"]},
  "oewn-00740055-s" : {"lexicalEntry":["oewn-scorched-s"]},
  "oewn-02470951-a" : {"lexicalEntry":["oewn-false-a"]},
  "oewn-07505182-n" : {"lexicalEntry":["oewn-satyriasis-n"]},
  "oewn-11484542-n" : {"lexicalEntry":["oewn-gravity-n","oewn-gravitation-n","oewn-gravitational_attraction-n","oewn-gravitational_force-n"]},
  "oewn-07520777-n" : {"lexicalEntry":["oewn-unconcern-n"]},
  "oewn-00385741-n" : {"lexicalEntry":["oewn-withdrawal-n","oewn-secession-n"]},
  "oewn-05815314-n" : {"lexicalEntry":["oewn-insight-n","oewn-brainwave-n","oewn-brainstorm-n"]},
  "oewn-08573923-n" : {"lexicalEntry":["oewn-distance-n"]},
  "oewn-02888703-n" : {"lexicalEntry":["oewn-boxing_glove-n","oewn-glove-n"]},
  "oewn-04063830-n" : {"lexicalEntry":["oewn-Rayleigh_disk-n"]},
  "oewn-04403228-n" : {"lexicalEntry":["oewn-taw-n","oewn-shooter-n"]},
  "oewn-04288269-n" : {"lexicalEntry":["oewn-spitball-n"]},
  "oewn-03904633-n" : {"lexicalEntry":["oewn-patent_medicine-n"]},
  "oewn-03386296-n" : {"lexicalEntry":["oewn-force_pump-n"]},
  "oewn-00940607-n" : {"lexicalEntry":["oewn-etching-n","oewn-engraving-n"]},
  "oewn-03847186-n" : {"lexicalEntry":["oewn-business_office-n","oewn-office-n"]},
  "oewn-06797496-n" : {"lexicalEntry":["oewn-teaser-n","oewn-puzzle-n","oewn-mystifier-n","oewn-puzzler-n"]},
  "oewn-04110188-n" : {"lexicalEntry":["oewn-rolling_mill-n"]},
  "oewn-02912610-n" : {"lexicalEntry":["oewn-bubblejet-n","oewn-bubble_jet_printer-n","oewn-bubble-jet_printer-n"]},
  "oewn-13790294-n" : {"lexicalEntry":["oewn-kettle-n","oewn-kettleful-n"]},
  "oewn-04534477-n" : {"lexicalEntry":["oewn-ventriloquist-ap-s_dummy-n"]},
  "oewn-05333608-n" : {"lexicalEntry":["oewn-lamella-n"]},
  "oewn-03533280-n" : {"lexicalEntry":["oewn-nursing_home-n","oewn-rest_home-n","oewn-home-n"]},
  "oewn-03120051-n" : {"lexicalEntry":["oewn-cotton_flannel-n","oewn-Canton_flannel-n"]},
  "oewn-03412654-n" : {"lexicalEntry":["oewn-fusee-n","oewn-fuzee-n"]},
  "oewn-05051127-n" : {"lexicalEntry":["oewn-exposure-n"]},
  "oewn-04553767-n" : {"lexicalEntry":["oewn-walk-up-n"]},
  "oewn-02794688-n" : {"lexicalEntry":["oewn-barbacan-n","oewn-barbican-n"]},
  "oewn-04216450-n" : {"lexicalEntry":["oewn-showerhead-n"]},
  "oewn-03592884-n" : {"lexicalEntry":["oewn-isoniazid-n","oewn-INH-n","oewn-Nydrazid-n"]},
  "oewn-02739803-n" : {"lexicalEntry":["oewn-argyle-n","oewn-argyll-n"]},
  "oewn-09271940-n" : {"lexicalEntry":["oewn-gap-n","oewn-col-n"]},
  "oewn-06584658-n" : {"lexicalEntry":["oewn-job-n"]},
  "oewn-04117272-n" : {"lexicalEntry":["oewn-rose_window-n","oewn-rosette-n"]},
  "oewn-04363682-n" : {"lexicalEntry":["oewn-sunhat-n","oewn-sun_hat-n"]},
  "oewn-04076889-n" : {"lexicalEntry":["oewn-training_school-n","oewn-reformatory-n","oewn-reform_school-n"]},
  "oewn-03031618-n" : {"lexicalEntry":["oewn-Channel_Tunnel-n","oewn-chunnel-n"]},
  "oewn-04392756-n" : {"lexicalEntry":["oewn-tailrace-n"]},
  "oewn-02783338-n" : {"lexicalEntry":["oewn-roller_bearing-n","oewn-ball_bearing-n","oewn-needle_bearing-n"]},
  "oewn-04619980-n" : {"lexicalEntry":["oewn-yellow_jack-n"]},
  "oewn-03708121-n" : {"lexicalEntry":["oewn-machmeter-n"]},
  "oewn-09324750-n" : {"lexicalEntry":["oewn-head-n"]},
  "oewn-03388492-n" : {"lexicalEntry":["oewn-smithy-n","oewn-forge-n"]},
  "oewn-10052950-n" : {"lexicalEntry":["oewn-dresser-n"]},
  "oewn-03314410-n" : {"lexicalEntry":["oewn-eyepiece-n","oewn-ocular-n"]},
  "oewn-05694495-n" : {"lexicalEntry":["oewn-inspiration-n","oewn-divine_guidance-n"]},
  "oewn-03990172-n" : {"lexicalEntry":["oewn-popper-n"]},
  "oewn-04294748-n" : {"lexicalEntry":["oewn-spray-n"]},
  "oewn-04938027-n" : {"lexicalEntry":["oewn-fast_lane-n"]},
  "oewn-03597088-n" : {"lexicalEntry":["oewn-jag-n","oewn-dag-n"]},
  "oewn-90000031-n" : {"lexicalEntry":["oewn-post-n"]},
  "oewn-04937316-n" : {"lexicalEntry":["oewn-drape-n"]},
  "oewn-04471653-n" : {"lexicalEntry":["oewn-caterpillar_track-n","oewn-caterpillar_tread-n","oewn-track-n"]},
  "oewn-03473502-n" : {"lexicalEntry":["oewn-gunboat-n"]},
  "oewn-03888751-n" : {"lexicalEntry":["oewn-panic_button-n"]},
  "oewn-14880143-n" : {"lexicalEntry":["oewn-vomit-n","oewn-puke-n","oewn-barf-n","oewn-vomitus-n"]},
  "oewn-03163551-n" : {"lexicalEntry":["oewn-sticker-n","oewn-dagger-n"]},
  "oewn-10212645-n" : {"lexicalEntry":["oewn-hunter-n","oewn-huntsman-n"]},
  "oewn-04510284-n" : {"lexicalEntry":["oewn-twenty-two_pistol-n"]},
  "oewn-04498607-n" : {"lexicalEntry":["oewn-trumpet_arch-n"]},
  "oewn-13512667-n" : {"lexicalEntry":["oewn-hatch-n","oewn-hatching-n"]},
  "oewn-05324741-n" : {"lexicalEntry":["oewn-capsule-n"]},
  "oewn-03975399-n" : {"lexicalEntry":["oewn-plumbing_system-n","oewn-plumbing-n"]},
  "oewn-03130521-n" : {"lexicalEntry":["oewn-craft-n"]},
  "oewn-08295090-n" : {"lexicalEntry":["oewn-college-n"]},
  "oewn-02920867-n" : {"lexicalEntry":["oewn-bullion-n"]},
  "oewn-03500164-n" : {"lexicalEntry":["oewn-harness-n"]},
  "oewn-03032590-n" : {"lexicalEntry":["oewn-Churchill_Downs-n"]},
  "oewn-07179737-n" : {"lexicalEntry":["oewn-tender-n","oewn-bid-n"]},
  "oewn-08086966-n" : {"lexicalEntry":["oewn-bucket_shop-n"]},
  "oewn-13391621-n" : {"lexicalEntry":["oewn-treasure-n"]},
  "oewn-03341227-n" : {"lexicalEntry":["oewn-figure_skate-n"]},
  "oewn-03393557-n" : {"lexicalEntry":["oewn-four-pounder-n"]},
  "oewn-04307879-n" : {"lexicalEntry":["oewn-stand-n"]},
  "oewn-03873920-n" : {"lexicalEntry":["oewn-oxcart-n"]},
  "oewn-09929118-n" : {"lexicalEntry":["oewn-charcoal_burner-n"]},
  "oewn-92461762-n" : {"lexicalEntry":["oewn-bowl_cutter-n","oewn-bowl_chopper-n"]},
  "oewn-92445022-n" : {"lexicalEntry":["oewn-chess_clock-n"]},
  "oewn-92449562-n" : {"lexicalEntry":["oewn-dental_chair-n"]},
  "oewn-04993179-n" : {"lexicalEntry":["oewn-treble-n","oewn-soprano-n"]},
  "oewn-01231134-n" : {"lexicalEntry":["oewn-attention-n"]},
  "oewn-04946223-n" : {"lexicalEntry":["oewn-limpness-n","oewn-flaccidity-n","oewn-flabbiness-n"]},
  "oewn-00723730-n" : {"lexicalEntry":["oewn-position-n"]},
  "oewn-06110385-n" : {"lexicalEntry":["oewn-optics-n"]},
  "oewn-05067645-n" : {"lexicalEntry":["oewn-abruptness-n","oewn-precipitance-n","oewn-precipitancy-n","oewn-precipitousness-n","oewn-suddenness-n","oewn-precipitateness-n"]},
  "oewn-04634724-n" : {"lexicalEntry":["oewn-uxoriousness-n"]},
  "oewn-04740358-n" : {"lexicalEntry":["oewn-aspect-n"]},
  "oewn-06814438-n" : {"lexicalEntry":["oewn-contour-n","oewn-contour_line-n"]},
  "oewn-04721334-n" : {"lexicalEntry":["oewn-normality-n"]},
  "oewn-04670676-n" : {"lexicalEntry":["oewn-inattentiveness-n"]},
  "oewn-04719195-n" : {"lexicalEntry":["oewn-flea_bite-n"]},
  "oewn-05120433-n" : {"lexicalEntry":["oewn-inadequacy-n","oewn-deficiency-n","oewn-insufficiency-n"]},
  "oewn-14519345-n" : {"lexicalEntry":["oewn-nastiness-n","oewn-filthiness-n","oewn-foulness-n","oewn-filth-n"]},
  "oewn-05116624-n" : {"lexicalEntry":["oewn-amplification-n","oewn-gain-n"]},
  "oewn-06212288-n" : {"lexicalEntry":["oewn-unfairness-n"]},
  "oewn-05102125-n" : {"lexicalEntry":["oewn-profundity-n","oewn-profoundness-n"]},
  "oewn-07766848-n" : {"lexicalEntry":["oewn-apricot-n"]},
  "oewn-05118811-n" : {"lexicalEntry":["oewn-correction-n"]},
  "oewn-07042575-n" : {"lexicalEntry":["oewn-signature-n","oewn-signature_tune-n","oewn-theme_song-n"]},
  "oewn-15286931-n" : {"lexicalEntry":["oewn-run-n"]},
  "oewn-14835366-n" : {"lexicalEntry":["oewn-chrome_green-n"]},
  "oewn-04817446-n" : {"lexicalEntry":["oewn-licitness-n"]},
  "oewn-07783320-n" : {"lexicalEntry":["oewn-olive-n"]},
  "oewn-01178605-n" : {"lexicalEntry":["oewn-battering-n","oewn-banging-n"]},
  "oewn-11525964-n" : {"lexicalEntry":["oewn-rejuvenation-n","oewn-greening-n"]},
  "oewn-05755760-n" : {"lexicalEntry":["oewn-stock-taking-n","oewn-stocktaking-n"]},
  "oewn-00893192-n" : {"lexicalEntry":["oewn-orientation-n","oewn-orientation_course-n"]},
  "oewn-01267968-n" : {"lexicalEntry":["oewn-beatification-n"]},
  "oewn-00426185-n" : {"lexicalEntry":["oewn-baiting-n"]},
  "oewn-00210529-n" : {"lexicalEntry":["oewn-pocket_veto-n"]},
  "oewn-00310889-n" : {"lexicalEntry":["oewn-geographic_expedition-n","oewn-exploration-n"]},
  "oewn-00451686-n" : {"lexicalEntry":["oewn-equestrian_sport-n"]},
  "oewn-00713150-n" : {"lexicalEntry":["oewn-predation-n"]},
  "oewn-01269438-n" : {"lexicalEntry":["oewn-stabilisation-n","oewn-stabilization-n"]},
  "oewn-00273147-n" : {"lexicalEntry":["oewn-bastardisation-n","oewn-bastardization-n"]},
  "oewn-00937062-n" : {"lexicalEntry":["oewn-ceramics-n"]},
  "oewn-09846765-n" : {"lexicalEntry":["oewn-baby-n"]},
  "oewn-01324712-n" : {"lexicalEntry":["oewn-baby-n"]},
  "oewn-00521115-n" : {"lexicalEntry":["oewn-Fat_Tuesday-n","oewn-Mardi_Gras-n"]},
  "oewn-00374670-n" : {"lexicalEntry":["oewn-ego_trip-n","oewn-self-aggrandisement-n","oewn-self-aggrandizement-n"]},
  "oewn-00133421-n" : {"lexicalEntry":["oewn-single-n","oewn-bingle-n"]},
  "oewn-01172992-n" : {"lexicalEntry":["oewn-riot-n","oewn-public_violence-n"]},
  "oewn-00908168-n" : {"lexicalEntry":["oewn-myelography-n"]},
  "oewn-00817305-n" : {"lexicalEntry":["oewn-aim-n"]},
  "oewn-14434647-n" : {"lexicalEntry":["oewn-situation-n"]},
  "oewn-00125437-n" : {"lexicalEntry":["oewn-shootout-n","oewn-gunfight-n","oewn-gunplay-n"]},
  "oewn-01067729-n" : {"lexicalEntry":["oewn-vacationing-n"]},
  "oewn-01092149-n" : {"lexicalEntry":["oewn-almsgiving-n","oewn-alms-giving-n"]},
  "oewn-00081439-n" : {"lexicalEntry":["oewn-covered_option-n"]},
  "oewn-07289021-n" : {"lexicalEntry":["oewn-nod-n"]},
  "oewn-01431211-v" : {"lexicalEntry":["oewn-make-v","oewn-score-v","oewn-seduce-v"]},
  "oewn-02236443-v" : {"lexicalEntry":["oewn-convey-v","oewn-transmit-v","oewn-communicate-v"]},
  "oewn-01111498-v" : {"lexicalEntry":["oewn-upset-v"]},
  "oewn-01348271-v" : {"lexicalEntry":["oewn-roll_up-v"]},
  "oewn-01940220-v" : {"lexicalEntry":["oewn-strike_out-v"]},
  "oewn-01237919-v" : {"lexicalEntry":["oewn-work-v","oewn-knead-v"]},
  "oewn-01416215-v" : {"lexicalEntry":["oewn-bat-v"]},
  "oewn-00518609-v" : {"lexicalEntry":["oewn-run-v"]},
  "oewn-00775477-v" : {"lexicalEntry":["oewn-fence-v","oewn-debate-v","oewn-contend-v","oewn-argue-v"]},
  "oewn-02253107-v" : {"lexicalEntry":["oewn-catch-v"]},
  "oewn-01157556-v" : {"lexicalEntry":["oewn-catch-v","oewn-overtake-v","oewn-catch_up_with-v"]},
  "oewn-02347796-v" : {"lexicalEntry":["oewn-flourish-v","oewn-thrive-v","oewn-fly_high-v","oewn-prosper-v"]},
  "oewn-02774217-v" : {"lexicalEntry":["oewn-shoot-v"]},
  "oewn-01842802-v" : {"lexicalEntry":["oewn-thrash-v"]},
  "oewn-02730001-v" : {"lexicalEntry":["oewn-cloister-v"]},
  "oewn-02615474-v" : {"lexicalEntry":["oewn-kick_in-v","oewn-set_in-v"]},
  "oewn-00195256-v" : {"lexicalEntry":["oewn-strip-v","oewn-bare-v","oewn-denude-v","oewn-denudate-v"]},
  "oewn-02109731-v" : {"lexicalEntry":["oewn-sling-v"]},
  "oewn-02565025-v" : {"lexicalEntry":["oewn-undo-v"]},
  "oewn-01970046-v" : {"lexicalEntry":["oewn-bolt-v"]},
  "oewn-02767855-v" : {"lexicalEntry":["oewn-extinguish-v","oewn-blow_out-v","oewn-quench-v","oewn-snuff_out-v"]},
  "oewn-02714161-v" : {"lexicalEntry":["oewn-misspend-v"]},
  "oewn-02140736-v" : {"lexicalEntry":["oewn-reverberate-v","oewn-reflect-v"]},
  "oewn-00812833-v" : {"lexicalEntry":["oewn-go_around-v","oewn-get_around-v","oewn-short-circuit-v","oewn-bypass-v"]},
  "oewn-02694636-v" : {"lexicalEntry":["oewn-overlap-v"]},
  "oewn-13793430-n" : {"lexicalEntry":["oewn-couple-n"]},
  "oewn-09381255-n" : {"lexicalEntry":["oewn-moon-n","oewn-Moon-n"]},
  "oewn-09302776-n" : {"lexicalEntry":["oewn-fireball-n"]},
  "oewn-09597144-n" : {"lexicalEntry":["oewn-Jupiter-n","oewn-Jove-n"]},
  "oewn-09346566-n" : {"lexicalEntry":["oewn-kaon-n","oewn-kappa-meson-n","oewn-K_particle-n","oewn-k-meson-n"]},
  "oewn-09337169-n" : {"lexicalEntry":["oewn-interplanetary_dust-n"]},
  "oewn-01821050-n" : {"lexicalEntry":["oewn-Ara-n","oewn-genus_Ara-n"]},
  "oewn-09307823-n" : {"lexicalEntry":["oewn-Fountain_of_Youth-n"]},
  "oewn-11516903-n" : {"lexicalEntry":["oewn-intraocular_pressure-n","oewn-IOP-n"]},
  "oewn-11500921-n" : {"lexicalEntry":["oewn-paramagnetism-n"]},
  "oewn-11452269-n" : {"lexicalEntry":["oewn-sea_breeze-n"]},
  "oewn-11186494-n" : {"lexicalEntry":["oewn-J._C._Maxwell-n","oewn-Maxwell-n","oewn-James_Clerk_Maxwell-n"]},
  "oewn-10531242-n" : {"lexicalEntry":["oewn-recitalist-n"]},
  "oewn-11229296-n" : {"lexicalEntry":["oewn-Norman-n","oewn-Greg_Norman-n","oewn-Gregory_John_Norman-n"]},
  "oewn-10390654-n" : {"lexicalEntry":["oewn-wine_lover-n"]},
  "oewn-06970027-n" : {"lexicalEntry":["oewn-Mari-n","oewn-Cheremis-n","oewn-Cheremiss-n","oewn-Mari_language-n","oewn-Cheremis_language-n","oewn-Cheremiss_language-n"]},
  "oewn-06530059-n" : {"lexicalEntry":["oewn-voucher-n","oewn-coupon-n"]},
  "oewn-10645222-n" : {"lexicalEntry":["oewn-thaumaturgist-n","oewn-thaumaturge-n","oewn-magician-n","oewn-wizard-n","oewn-necromancer-n","oewn-sorcerer-n"]},
  "oewn-09707883-n" : {"lexicalEntry":["oewn-Gaul-n"]},
  "oewn-10001900-n" : {"lexicalEntry":["oewn-cultist-n"]},
  "oewn-10532452-n" : {"lexicalEntry":["oewn-recruiting-sergeant-n"]},
  "oewn-10353968-n" : {"lexicalEntry":["oewn-motorman-n"]},
  "oewn-10287416-n" : {"lexicalEntry":["oewn-Little_Red_Riding_Hood-n"]},
  "oewn-10909657-n" : {"lexicalEntry":["oewn-Sir_William_Chambers-n","oewn-William_Chambers-n","oewn-Chambers-n"]},
  "oewn-10030421-n" : {"lexicalEntry":["oewn-devisor-n"]},
  "oewn-11324456-n" : {"lexicalEntry":["oewn-Skinner-n","oewn-B._F._Skinner-n","oewn-Burrhus_Frederic_Skinner-n","oewn-Fred_Skinner-n"]},
  "oewn-11005834-n" : {"lexicalEntry":["oewn-Robert_Fulton-n","oewn-Fulton-n"]},
  "oewn-10324172-n" : {"lexicalEntry":["oewn-meat_packer-n","oewn-packer-n"]},
  "oewn-10107343-n" : {"lexicalEntry":["oewn-filer-n","oewn-filing_clerk-n","oewn-file_clerk-n"]},
  "oewn-10609074-n" : {"lexicalEntry":["oewn-ship-breaker-n"]},
  "oewn-09730831-n" : {"lexicalEntry":["oewn-Laconian-n"]},
  "oewn-09760285-n" : {"lexicalEntry":["oewn-Alaskan-n"]},
  "oewn-11347645-n" : {"lexicalEntry":["oewn-Arthur_Symons-n","oewn-Symons-n"]},
  "oewn-09933282-n" : {"lexicalEntry":["oewn-chemist-n"]},
  "oewn-10694697-n" : {"lexicalEntry":["oewn-sun_worshiper-n"]},
  "oewn-10703076-n" : {"lexicalEntry":["oewn-swineherd-n","oewn-pigman-n"]},
  "oewn-09613669-n" : {"lexicalEntry":["oewn-Brunnhilde-n","oewn-Brunhild-n","oewn-Brynhild-n","oewn-Brynhildr-n"]},
  "oewn-09608108-n" : {"lexicalEntry":["oewn-Ymir-n"]},
  "oewn-10500315-n" : {"lexicalEntry":["oewn-professor-n","oewn-prof-n"]},
  "oewn-09837427-n" : {"lexicalEntry":["oewn-spaceman-n","oewn-astronaut-n","oewn-cosmonaut-n"]},
  "oewn-10516410-n" : {"lexicalEntry":["oewn-pyromancer-n"]},
  "oewn-10498412-n" : {"lexicalEntry":["oewn-proctologist-n"]},
  "oewn-08232722-n" : {"lexicalEntry":["oewn-bodyguard-n"]},
  "oewn-06993497-n" : {"lexicalEntry":["oewn-Savara-n","oewn-Savara_language-n"]},
  "oewn-10384032-n" : {"lexicalEntry":["oewn-Nubian-n"]},
  "oewn-11263710-n" : {"lexicalEntry":["oewn-Emily_Price_Post-n","oewn-Post-n","oewn-Emily_Post-n"]},
  "oewn-09630812-n" : {"lexicalEntry":["oewn-argonaut-n"]},
  "oewn-11062686-n" : {"lexicalEntry":["oewn-Henry_VI-n","oewn-Henry_VI_of_England-n"]},
  "oewn-10493374-n" : {"lexicalEntry":["oewn-princeling-n"]},
  "oewn-11265372-n" : {"lexicalEntry":["oewn-Powhatan-n","oewn-Wahunsonacock-n"]},
  "oewn-10891513-n" : {"lexicalEntry":["oewn-Richard_Burbage-n","oewn-Burbage-n"]},
  "oewn-06991187-n" : {"lexicalEntry":["oewn-Circassian-n","oewn-Circassian_language-n"]},
  "oewn-10891242-n" : {"lexicalEntry":["oewn-Luis_Bunuel-n","oewn-Bunuel-n"]},
  "oewn-09995336-n" : {"lexicalEntry":["oewn-crammer-n"]},
  "oewn-07651436-n" : {"lexicalEntry":["oewn-butter_cookie-n"]},
  "oewn-07954389-n" : {"lexicalEntry":["oewn-vitamin_pill-n"]},
  "oewn-07692600-n" : {"lexicalEntry":["oewn-Vienna_sausage-n"]},
  "oewn-11716068-n" : {"lexicalEntry":["oewn-papaw-n","oewn-pawpaw-n","oewn-Asimina_triloba-n","oewn-papaw_tree-n"]},
  "oewn-07621206-n" : {"lexicalEntry":["oewn-chocolate_fudge-n"]},
  "oewn-11778122-n" : {"lexicalEntry":["oewn-mimosa-n","oewn-silver_wattle-n","oewn-Acacia_dealbata-n"]},
  "oewn-07746009-n" : {"lexicalEntry":["oewn-cardoon-n"]},
  "oewn-12041968-n" : {"lexicalEntry":["oewn-costmary-n","oewn-Tanacetum_balsamita-n","oewn-Chrysanthemum_balsamita-n","oewn-bible_leaf-n","oewn-mint_geranium-n","oewn-alecost-n","oewn-balsam_herb-n"]},
  "oewn-07661378-n" : {"lexicalEntry":["oewn-Oven_Stuffer-n","oewn-Oven_Stuffer_Roaster-n"]},
  "oewn-07954667-n" : {"lexicalEntry":["oewn-slop-n"]},
  "oewn-07611220-n" : {"lexicalEntry":["oewn-cane_sugar-n"]},
  "oewn-07697550-n" : {"lexicalEntry":["oewn-cracked-wheat_bread-n"]},
  "oewn-12144165-n" : {"lexicalEntry":["oewn-barleycorn-n"]},
  "oewn-07731779-n" : {"lexicalEntry":["oewn-yellow_squash-n"]},
  "oewn-07786265-n" : {"lexicalEntry":["oewn-sour_gourd-n"]},
  "oewn-07698784-n" : {"lexicalEntry":["oewn-graham_bread-n"]},
  "oewn-07637670-n" : {"lexicalEntry":["oewn-baked_goods-n"]},
  "oewn-06506007-n" : {"lexicalEntry":["oewn-playlist-n","oewn-play_list-n"]},
  "oewn-06724644-n" : {"lexicalEntry":["oewn-counterblast-n"]},
  "oewn-07042284-n" : {"lexicalEntry":["oewn-leitmotiv-n","oewn-leitmotif-n"]},
  "oewn-13661999-n" : {"lexicalEntry":["oewn-L-n","oewn-lambert-n"]},
  "oewn-05832071-n" : {"lexicalEntry":["oewn-descriptor-n"]},
  "oewn-06806967-n" : {"lexicalEntry":["oewn-street_sign-n"]},
  "oewn-07083114-n" : {"lexicalEntry":["oewn-ecobabble-n"]},
  "oewn-06708324-n" : {"lexicalEntry":["oewn-flattery-n"]},
  "oewn-14949053-n" : {"lexicalEntry":["oewn-jargon-n","oewn-jargoon-n"]},
  "oewn-07480588-n" : {"lexicalEntry":["oewn-series-n"]},
  "oewn-07009415-n" : {"lexicalEntry":["oewn-Serer-n","oewn-Serer_language-n"]},
  "oewn-06281343-n" : {"lexicalEntry":["oewn-credendum-n","oewn-article_of_faith-n"]},
  "oewn-06751572-n" : {"lexicalEntry":["oewn-explanandum-n","oewn-explicandum-n"]},
  "oewn-06527045-n" : {"lexicalEntry":["oewn-family_history-n"]},
  "oewn-06358261-n" : {"lexicalEntry":["oewn-caption-n","oewn-legend-n"]},
  "oewn-07017680-n" : {"lexicalEntry":["oewn-electroretinogram-n"]},
  "oewn-13611282-n" : {"lexicalEntry":["oewn-R-n","oewn-universal_gas_constant-n","oewn-gas_constant-n"]},
  "oewn-06584830-n" : {"lexicalEntry":["oewn-word_processing_system-n","oewn-word_processor-n"]},
  "oewn-07176264-n" : {"lexicalEntry":["oewn-contract_offer-n"]},
  "oewn-06341757-n" : {"lexicalEntry":["oewn-phrasal_verb-n"]},
  "oewn-06414613-n" : {"lexicalEntry":["oewn-triple-spacing-n"]},
  "oewn-07040407-n" : {"lexicalEntry":["oewn-musical_drama-n"]},
  "oewn-00366673-v" : {"lexicalEntry":["oewn-sublimate-v","oewn-sublime-v"]},
  "oewn-01864606-v" : {"lexicalEntry":["oewn-flag_down-v"]},
  "oewn-01948551-v" : {"lexicalEntry":["oewn-boat-v"]},
  "oewn-01142049-v" : {"lexicalEntry":["oewn-double_up-v","oewn-parlay-v"]},
  "oewn-01953438-v" : {"lexicalEntry":["oewn-wheelbarrow-v"]},
  "oewn-01838302-v" : {"lexicalEntry":["oewn-whish-v"]},
  "oewn-02029675-v" : {"lexicalEntry":["oewn-escort-v"]},
  "oewn-01003339-v" : {"lexicalEntry":["oewn-set_forth-v","oewn-exposit-v","oewn-expound-v"]},
  "oewn-01775311-v" : {"lexicalEntry":["oewn-move-v"]},
  "oewn-02053912-v" : {"lexicalEntry":["oewn-get_by-v"]},
  "oewn-02161274-v" : {"lexicalEntry":["oewn-clear-v"]},
  "oewn-02044779-v" : {"lexicalEntry":["oewn-genuflect-v"]},
  "oewn-00669020-v" : {"lexicalEntry":["oewn-nullify-v","oewn-invalidate-v"]},
  "oewn-02380015-v" : {"lexicalEntry":["oewn-presume-v","oewn-make_bold-v","oewn-dare-v"]},
  "oewn-00651669-v" : {"lexicalEntry":["oewn-discriminate-v","oewn-know_apart-v"]},
  "oewn-06136212-n" : {"lexicalEntry":["oewn-biotech-n","oewn-biotechnology-n"]},
  "oewn-05884595-n" : {"lexicalEntry":["oewn-Boyle-ap-s_law-n","oewn-Mariotte-ap-s_law-n"]},
  "oewn-06154306-n" : {"lexicalEntry":["oewn-Egyptology-n"]},
  "oewn-06244979-n" : {"lexicalEntry":["oewn-Mohammedanism-n","oewn-Islamism-n","oewn-Muhammadanism-n","oewn-Islam-n","oewn-Muslimism-n"]},
  "oewn-08406169-n" : {"lexicalEntry":["oewn-musketry-n"]},
  "oewn-05945713-n" : {"lexicalEntry":["oewn-auditory_image-n"]},
  "oewn-06121335-n" : {"lexicalEntry":["oewn-statistical_mechanics-n"]},
  "oewn-05766545-n" : {"lexicalEntry":["oewn-woodcraft-n"]},
  "oewn-05651652-n" : {"lexicalEntry":["oewn-priestcraft-n"]},
  "oewn-05695974-n" : {"lexicalEntry":["oewn-hydra-n"]},
  "oewn-92441936-n" : {"lexicalEntry":["oewn-Slavophilism-n","oewn-Slavophilia-n"]},
  "oewn-01125456-v" : {"lexicalEntry":["oewn-chicken-fight-v","oewn-chickenfight-v"]},
  "oewn-01156228-v" : {"lexicalEntry":["oewn-get_even-v","oewn-get_back-v"]},
  "oewn-02502465-v" : {"lexicalEntry":["oewn-subject-v","oewn-subjugate-v"]},
  "oewn-01090140-v" : {"lexicalEntry":["oewn-forearm-v"]},
  "oewn-02426849-v" : {"lexicalEntry":["oewn-bail-v"]},
  "oewn-00970070-v" : {"lexicalEntry":["oewn-edit-v"]},
  "oewn-00506593-v" : {"lexicalEntry":["oewn-devitrify-v"]},
  "oewn-00377673-v" : {"lexicalEntry":["oewn-burn-v","oewn-combust-v"]},
  "oewn-02601659-v" : {"lexicalEntry":["oewn-repeat-v","oewn-take_over-v"]},
  "oewn-00508745-v" : {"lexicalEntry":["oewn-fossilize-v","oewn-fossilise-v"]},
  "oewn-02529450-v" : {"lexicalEntry":["oewn-fail-v"]},
  "oewn-00172922-v" : {"lexicalEntry":["oewn-fail-v"]},
  "oewn-00910304-v" : {"lexicalEntry":["oewn-foster-v","oewn-nurture-v"]},
  "oewn-02496911-v" : {"lexicalEntry":["oewn-jubilate-v"]},
  "oewn-02376775-v" : {"lexicalEntry":["oewn-partner-v"]},
  "oewn-02480532-v" : {"lexicalEntry":["oewn-bat_mitzvah-v"]},
  "oewn-01594338-n" : {"lexicalEntry":["oewn-tit-n","oewn-titmouse-n"]},
  "oewn-05551711-n" : {"lexicalEntry":["oewn-frontal_suture-n","oewn-sutura_frontalis-n"]},
  "oewn-05347865-n" : {"lexicalEntry":["oewn-truncus_celiacus-n","oewn-celiac_trunk-n","oewn-celiac_artery-n","oewn-arteria_celiaca-n"]},
  "oewn-05432784-n" : {"lexicalEntry":["oewn-vena_vertebralis-n","oewn-vertebral_vein-n"]},
  "oewn-02168177-v" : {"lexicalEntry":["oewn-sight-v","oewn-spy-v"]},
  "oewn-00960110-v" : {"lexicalEntry":["oewn-reecho-v"]},
  "oewn-14833081-n" : {"lexicalEntry":["oewn-ethanoyl_chloride-n","oewn-acetyl_chloride-n"]},
  "oewn-14993314-n" : {"lexicalEntry":["oewn-oleoresin_capiscum-n"]},
  "oewn-14641605-n" : {"lexicalEntry":["oewn-allyl-n","oewn-allyl_radical-n","oewn-allyl_group-n"]},
  "oewn-14617524-n" : {"lexicalEntry":["oewn-thermoplastic_resin-n","oewn-thermoplastic-n"]},
  "oewn-14704997-n" : {"lexicalEntry":["oewn-maltha-n","oewn-mineral_tar-n"]},
  "oewn-15043924-n" : {"lexicalEntry":["oewn-water_sapphire-n"]},
  "oewn-15057630-n" : {"lexicalEntry":["oewn-gingerol-n"]},
  "oewn-14919750-n" : {"lexicalEntry":["oewn-kauri_resin-n","oewn-kauri-n","oewn-kauri_copal-n","oewn-kauri_gum-n"]},
  "oewn-15070057-n" : {"lexicalEntry":["oewn-sodium_hypochlorite-n"]},
  "oewn-14649636-n" : {"lexicalEntry":["oewn-metal-n","oewn-metallic_element-n"]},
  "oewn-15033893-n" : {"lexicalEntry":["oewn-freshwater-n","oewn-fresh_water-n"]},
  "oewn-14710746-n" : {"lexicalEntry":["oewn-heating_oil-n","oewn-fuel_oil-n"]},
  "oewn-14831907-n" : {"lexicalEntry":["oewn-monoamine_neurotransmitter-n"]},
  "oewn-07451586-n" : {"lexicalEntry":["oewn-impregnation-n","oewn-fertilization-n","oewn-fertilisation-n","oewn-fecundation-n"]},
  "oewn-14666183-n" : {"lexicalEntry":["oewn-iodine-125-n"]},
  "oewn-14614865-n" : {"lexicalEntry":["oewn-hydrogel-n"]},
  "oewn-08330720-n" : {"lexicalEntry":["oewn-Constantinople-n","oewn-First_Council_of_Constantinople-n"]},
  "oewn-08818528-n" : {"lexicalEntry":["oewn-Byzantium-n","oewn-Byzantine_Empire-n","oewn-Eastern_Roman_Empire-n"]},
  "oewn-08965960-n" : {"lexicalEntry":["oewn-Ghana-n","oewn-Gold_Coast-n","oewn-Republic_of_Ghana-n"]},
  "oewn-09039375-n" : {"lexicalEntry":["oewn-Odessa-n","oewn-Odesa-n"]},
  "oewn-08856449-n" : {"lexicalEntry":["oewn-Kolonia-n"]},
  "oewn-08571577-n" : {"lexicalEntry":["oewn-retirement_community-n","oewn-retirement_complex-n"]},
  "oewn-09070583-n" : {"lexicalEntry":["oewn-East_Coast-n","oewn-East_Coast_of_the_United_States-n"]},
  "oewn-09148020-n" : {"lexicalEntry":["oewn-Schenectady-n"]},
  "oewn-02264354-v" : {"lexicalEntry":["oewn-chaffer-v","oewn-haggle-v","oewn-huckster-v","oewn-higgle-v"]},
  "oewn-01649543-n" : {"lexicalEntry":["oewn-Bufo_viridis-n","oewn-Eurasian_green_toad-n"]},
  "oewn-02668043-n" : {"lexicalEntry":["oewn-thick_skin-n"]},
  "oewn-01536534-n" : {"lexicalEntry":["oewn-crossbill-n","oewn-Loxia_curvirostra-n"]},
  "oewn-02010695-n" : {"lexicalEntry":["oewn-heron-n"]},
  "oewn-01923700-n" : {"lexicalEntry":["oewn-Cestum_veneris-n","oewn-Venus-ap-s_girdle-n"]},
  "oewn-01492142-n" : {"lexicalEntry":["oewn-bull_shark-n","oewn-Carcharhinus_leucas-n","oewn-cub_shark-n"]},
  "oewn-02120298-n" : {"lexicalEntry":["oewn-brown_hyena-n","oewn-strand_wolf-n","oewn-Hyaena_brunnea-n"]},
  "oewn-02625342-n" : {"lexicalEntry":["oewn-oilfish-n","oewn-Ruvettus_pretiosus-n"]},
  "oewn-01613399-n" : {"lexicalEntry":["oewn-family_Falconidae-n","oewn-Falconidae-n"]},
  "oewn-11924350-n" : {"lexicalEntry":["oewn-genus_Corydalis-n","oewn-Corydalis-n"]},
  "oewn-02000259-n" : {"lexicalEntry":["oewn-fish_louse-n"]},
  "oewn-02298802-n" : {"lexicalEntry":["oewn-Cerapteryx-n","oewn-genus_Cerapteryx-n"]},
  "oewn-02237371-n" : {"lexicalEntry":["oewn-genus_Blattella-n","oewn-Blattella-n"]},
  "oewn-02187989-n" : {"lexicalEntry":["oewn-Mallophaga-n","oewn-order_Mallophaga-n"]},
  "oewn-01710207-n" : {"lexicalEntry":["oewn-genus_Iguanodon-n"]},
  "oewn-02180427-n" : {"lexicalEntry":["oewn-deathwatch_beetle-n","oewn-deathwatch-n","oewn-Xestobium_rufovillosum-n"]},
  "oewn-02425345-n" : {"lexicalEntry":["oewn-impala-n","oewn-Aepyceros_melampus-n"]},
  "oewn-02588077-n" : {"lexicalEntry":["oewn-swimmeret-n","oewn-pleopod-n"]},
  "oewn-01751327-n" : {"lexicalEntry":["oewn-black-necked_cobra-n","oewn-Naja_nigricollis-n","oewn-spitting_cobra-n"]},
  "oewn-02535082-n" : {"lexicalEntry":["oewn-Clupea_harengus_pallasii-n","oewn-Pacific_herring-n"]},
  "oewn-01392764-n" : {"lexicalEntry":["oewn-sarcodine-n","oewn-sarcodinian-n"]},
  "oewn-02203357-n" : {"lexicalEntry":["oewn-genus_Aedes-n","oewn-Aedes-n"]},
  "oewn-01675759-n" : {"lexicalEntry":["oewn-genus_Sphenodon-n","oewn-Sphenodon-n"]},
  "oewn-02013107-n" : {"lexicalEntry":["oewn-night_heron-n","oewn-night_raven-n"]},
  "oewn-02627762-n" : {"lexicalEntry":["oewn-genus_Acanthocybium-n","oewn-Acanthocybium-n"]},
  "oewn-01948918-n" : {"lexicalEntry":["oewn-neritid_gastropod-n","oewn-neritid-n"]},
  "oewn-02589496-n" : {"lexicalEntry":["oewn-Lutjanus-n","oewn-genus_Lutjanus-n"]},
  "oewn-02224851-n" : {"lexicalEntry":["oewn-Myrmecia-n","oewn-genus_Myrmecia-n"]},
  "oewn-02381835-n" : {"lexicalEntry":["oewn-quarter_horse-n"]},
  "oewn-02219017-n" : {"lexicalEntry":["oewn-mud_dauber-n"]},
  "oewn-02048023-n" : {"lexicalEntry":["oewn-auk-n"]},
  "oewn-01366360-n" : {"lexicalEntry":["oewn-spirillum-n"]},
  "oewn-01414091-n" : {"lexicalEntry":["oewn-chlorella-n"]},
  "oewn-12933904-n" : {"lexicalEntry":["oewn-butterfly_flower-n","oewn-schizanthus-n","oewn-poor_man-ap-s_orchid-n"]},
  "oewn-12836685-n" : {"lexicalEntry":["oewn-family_Boraginaceae-n","oewn-Boraginaceae-n","oewn-borage_family-n"]},
  "oewn-13240156-n" : {"lexicalEntry":["oewn-Equisetum-n","oewn-genus_Equisetum-n"]},
  "oewn-12939955-n" : {"lexicalEntry":["oewn-tramp-ap-s_spurge-n","oewn-flowering_spurge-n","oewn-wild_spurge-n","oewn-Euphorbia_corollata-n"]},
  "oewn-12537089-n" : {"lexicalEntry":["oewn-glory_pea-n","oewn-clianthus-n"]},
  "oewn-12009243-n" : {"lexicalEntry":["oewn-genus_Leontodon-n","oewn-Leontodon-n"]},
  "oewn-12051123-n" : {"lexicalEntry":["oewn-crown_beard-n","oewn-crown-beard-n","oewn-crownbeard-n"]},
  "oewn-13195721-n" : {"lexicalEntry":["oewn-cow-tongue_fern-n","oewn-Florida_strap_fern-n","oewn-hart-ap-s-tongue_fern-n"]},
  "oewn-13175531-n" : {"lexicalEntry":["oewn-lily_pad-n"]},
  "oewn-12274352-n" : {"lexicalEntry":["oewn-Port_Jackson_heath-n","oewn-Epacris_purpurascens-n"]},
  "oewn-12833561-n" : {"lexicalEntry":["oewn-Graptophyllum_pictum-n","oewn-caricature_plant-n"]},
  "oewn-12098952-n" : {"lexicalEntry":["oewn-Platanthera_leucophea-n","oewn-prairie_white-fringed_orchid-n"]},
  "oewn-12624989-n" : {"lexicalEntry":["oewn-garden_sorrel-n","oewn-Rumex_acetosa-n","oewn-sour_dock-n"]},
  "oewn-12340802-n" : {"lexicalEntry":["oewn-hickory-n"]},
  "oewn-13107198-n" : {"lexicalEntry":["oewn-cover_crop-n"]},
  "oewn-11876524-n" : {"lexicalEntry":["oewn-genus_Agdestis-n","oewn-Agdestis-n"]},
  "oewn-11643556-n" : {"lexicalEntry":["oewn-cedar-n","oewn-cedar_tree-n","oewn-true_cedar-n"]},
  "oewn-13229036-n" : {"lexicalEntry":["oewn-genus_Anogramma-n","oewn-Anogramma-n"]},
  "oewn-12414635-n" : {"lexicalEntry":["oewn-Laportea_canadensis-n","oewn-wood_nettle-n"]},
  "oewn-11760447-n" : {"lexicalEntry":["oewn-winter-ap-s_bark_tree-n","oewn-Drimys_winteri-n","oewn-winter-ap-s_bark-n"]},
  "oewn-12014996-n" : {"lexicalEntry":["oewn-Chile_tarweed-n","oewn-melosa-n","oewn-madia_oil_plant-n","oewn-Madia_sativa-n"]},
  "oewn-11677765-n" : {"lexicalEntry":["oewn-genus_Nageia-n","oewn-Nageia-n"]},
  "oewn-12144689-n" : {"lexicalEntry":["oewn-little_barley-n","oewn-Hordeum_pusillum-n"]},
  "oewn-13059337-n" : {"lexicalEntry":["oewn-Gyromitra_brunnea-n","oewn-Gyromitra_fastigiata-n"]},
  "oewn-11919496-n" : {"lexicalEntry":["oewn-Thysanocarpus-n","oewn-genus_Thysanocarpus-n"]},
  "oewn-11649662-n" : {"lexicalEntry":["oewn-genus_Cathaya-n"]},
  "oewn-12654627-n" : {"lexicalEntry":["oewn-applewood-n"]},
  "oewn-15254204-n" : {"lexicalEntry":["oewn-canonical_hour-n"]},
  "oewn-15150471-n" : {"lexicalEntry":["oewn-Miocene-n","oewn-Miocene_epoch-n"]},
  "oewn-15160652-n" : {"lexicalEntry":["oewn-circadian_rhythm-n"]},
  "oewn-02785392-a" : {"lexicalEntry":["oewn-parous-a"]},
  "oewn-02887011-a" : {"lexicalEntry":["oewn-cutaneal-a","oewn-cutaneous-a","oewn-dermal-a"]},
  "oewn-02872948-a" : {"lexicalEntry":["oewn-optical-a"]},
  "oewn-02838835-a" : {"lexicalEntry":["oewn-hydroelectric-a"]},
  "oewn-02761013-a" : {"lexicalEntry":["oewn-intraventricular-a"]},
  "oewn-03022172-a" : {"lexicalEntry":["oewn-vertebral-a"]},
  "oewn-02927716-a" : {"lexicalEntry":["oewn-exodontic-a"]},
  "oewn-02976174-a" : {"lexicalEntry":["oewn-Bosnian-a"]},
  "oewn-00372967-r" : {"lexicalEntry":["oewn-inconspicuously-r"]},
  "oewn-00271442-r" : {"lexicalEntry":["oewn-aground-r"]},
  "oewn-00177625-r" : {"lexicalEntry":["oewn-creatively-r"]},
  "oewn-00324586-r" : {"lexicalEntry":["oewn-dumbly-r"]},
  "oewn-00493490-r" : {"lexicalEntry":["oewn-usefully-r"]},
  "oewn-00517831-r" : {"lexicalEntry":["oewn-stably-r"]},
  "oewn-00466398-r" : {"lexicalEntry":["oewn-unsuspectingly-r"]},
  "oewn-00368062-r" : {"lexicalEntry":["oewn-personally-r"]},
  "oewn-00313996-r" : {"lexicalEntry":["oewn-disagreeably-r"]},
  "oewn-00518777-r" : {"lexicalEntry":["oewn-ulteriorly-r"]},
  "oewn-00258865-r" : {"lexicalEntry":["oewn-sine_die-r"]},
  "oewn-00267447-r" : {"lexicalEntry":["oewn-arrogantly-r"]},
  "oewn-00431708-r" : {"lexicalEntry":["oewn-predictably-r"]},
  "oewn-00088791-r" : {"lexicalEntry":["oewn-temporarily-r"]},
  "oewn-00210382-r" : {"lexicalEntry":["oewn-unimaginatively-r"]},
  "oewn-14326676-n" : {"lexicalEntry":["oewn-diuresis-n"]},
  "oewn-14188722-n" : {"lexicalEntry":["oewn-hemolytic_anemia-n","oewn-haemolytic_anaemia-n"]},
  "oewn-14217827-n" : {"lexicalEntry":["oewn-lysogenicity-n","oewn-lysogeny-n"]},
  "oewn-14274656-n" : {"lexicalEntry":["oewn-hepatoma-n","oewn-hepatocellular_carcinoma-n","oewn-hepatocarcinoma-n","oewn-malignant_hepatoma-n"]},
  "oewn-13264272-n" : {"lexicalEntry":["oewn-villeinage-n"]},
  "oewn-14434483-n" : {"lexicalEntry":["oewn-balance-of-payments_problem-n"]},
  "oewn-14223416-n" : {"lexicalEntry":["oewn-kwashiorkor-n"]},
  "oewn-13508612-n" : {"lexicalEntry":["oewn-glaciation-n"]},
  "oewn-14092010-n" : {"lexicalEntry":["oewn-fluorosis-n"]},
  "oewn-07477765-n" : {"lexicalEntry":["oewn-Grand_National-n"]},
  "oewn-08230899-n" : {"lexicalEntry":["oewn-brigade-n"]},
  "oewn-08144286-n" : {"lexicalEntry":["oewn-United_States_Postal_Service-n","oewn-USPS-n","oewn-US_Postal_Service-n"]},
  "oewn-08141631-n" : {"lexicalEntry":["oewn-Center_for_Disease_Control_and_Prevention-n","oewn-CDC-n"]},
  "oewn-08152044-n" : {"lexicalEntry":["oewn-HUD-n","oewn-Department_of_Housing_and_Urban_Development-n","oewn-Housing_and_Urban_Development-n"]},
  "oewn-08022847-n" : {"lexicalEntry":["oewn-price_bracket-n"]},
  "oewn-08340588-n" : {"lexicalEntry":["oewn-board_of_regents-n"]},
  "oewn-13291929-n" : {"lexicalEntry":["oewn-political_donation-n","oewn-political_contribution-n"]},
  "oewn-92440439-n" : {"lexicalEntry":["oewn-credit_balance-n","oewn-positive_balance-n"]},
  "oewn-01190273-v" : {"lexicalEntry":["oewn-famish-v","oewn-starve-v"]},
  "oewn-90013411-v" : {"lexicalEntry":["oewn-thug-v"]},
  "oewn-00921931-v" : {"lexicalEntry":["oewn-redetermine-v"]},
  "oewn-13522941-n" : {"lexicalEntry":["oewn-intussusception-n"]}
}