{
  "oewn-turn__2.38.02.." : [{"relType":"derivation","synset":"oewn-07366212-n","sense":"oewn-turn__1.11.00.."},{"relType":"derivation","synset":"oewn-00346280-n","sense":"oewn-turn__1.04.07.."}],
  "oewn-channelize__2.35.01.." : [{"relType":"derivation","synset":"oewn-03009709-n","sense":"oewn-channel__1.06.00.."}],
  "oewn-diametric__3.01.00.." : [{"relType":"derivation","synset":"oewn-05109077-n","sense":"oewn-diameter__1.07.00.."},{"relType":"derivation","synset":"oewn-13894356-n","sense":"oewn-diameter__1.25.00.."}],
  "oewn-anxiousness__1.12.00.." : [{"relType":"derivation","synset":"oewn-02465209-s","sense":"oewn-anxious__5.00.00.troubled.00"}],
  "oewn-official__3.00.00.." : [{"relType":"antonym","synset":"oewn-01637634-a","sense":"oewn-unofficial__3.00.00.."},{"relType":"derivation","synset":"oewn-13968154-n","sense":"oewn-office__1.26.00.."},{"relType":"pertainym","synset":"oewn-00188003-r","sense":"oewn-officially__4.02.01.."}],
  "oewn-heedlessness__1.09.00.." : [{"relType":"derivation","synset":"oewn-01197257-a","sense":"oewn-heedless__3.00.00.."}],
  "oewn-unicameral__3.00.00.." : [{"relType":"antonym","synset":"oewn-00234855-a","sense":"oewn-bicameral__3.00.00.."}],
  "oewn-violence__1.04.01.." : [{"relType":"derivation","synset":"oewn-01575140-s","sense":"oewn-violent__5.00.00.unnatural.00"}],
  "oewn-ungregarious__3.00.01.." : [{"relType":"antonym","synset":"oewn-02261145-a","sense":"oewn-gregarious__3.00.01.."}],
  "oewn-impendency__1.26.00.." : [{"relType":"derivation","synset":"oewn-00450348-s","sense":"oewn-impendent__5.00.00.close.01"},{"relType":"derivation","synset":"oewn-02732759-v","sense":"oewn-impend__2.42.00.."}],
  "oewn-richness__1.07.02.." : [{"relType":"derivation","synset":"oewn-02031394-a","sense":"oewn-rich__3.00.02.."},{"relType":"derivation","synset":"oewn-01085028-s","sense":"oewn-rich__5.00.00.fruitful.00"},{"relType":"derivation","synset":"oewn-01872379-s","sense":"oewn-rich__5.00.02.productive.00"}],
  "oewn-recumb__2.35.00.." : [{"relType":"derivation","synset":"oewn-01241074-s","sense":"oewn-recumbent__5.00.00.unerect.00"}],
  "oewn-contradictoriness__1.24.00.." : [{"relType":"derivation","synset":"oewn-02390712-s","sense":"oewn-contradictory__5.00.00.antonymous.00"},{"relType":"derivation","synset":"oewn-00580585-s","sense":"oewn-contradictory__5.00.00.inconsistent.00"},{"relType":"derivation","synset":"oewn-00510662-s","sense":"oewn-contradictory__5.00.00.incompatible.01"}],
  "oewn-foul__3.00.00.." : [{"relType":"antonym","synset":"oewn-00958816-a","sense":"oewn-fair__3.00.01.."}],
  "oewn-blood__1.08.00.." : [{"relType":"derivation","synset":"oewn-00248306-a","sense":"oewn-bloody__3.00.00.."},{"relType":"derivation","synset":"oewn-01236206-v","sense":"oewn-blood__2.35.00.."},{"relType":"pertainym","synset":"oewn-02861368-a","sense":"oewn-hemic__3.01.00.."},{"relType":"pertainym","synset":"oewn-02861368-a","sense":"oewn-haematic__3.01.00.."},{"relType":"pertainym","synset":"oewn-02861368-a","sense":"oewn-haemic__3.01.00.."},{"relType":"pertainym","synset":"oewn-02861368-a","sense":"oewn-hematic__3.01.00.."}],
  "oewn-literate__3.00.00.." : [{"relType":"antonym","synset":"oewn-01424552-a","sense":"oewn-illiterate__3.00.00.."}],
  "oewn-accretion__1.23.00.." : [{"relType":"derivation","synset":"oewn-02545807-s","sense":"oewn-accretionary__5.00.00.increasing.00"}],
  "oewn-unconventional__3.00.01.." : [{"relType":"antonym","synset":"oewn-00607893-a","sense":"oewn-conventional__3.00.00.."},{"relType":"antonym","synset":"oewn-00609798-a","sense":"oewn-conventional__3.00.01.."}],
  "oewn-poignancy__1.07.00.." : [{"relType":"derivation","synset":"oewn-01565214-s","sense":"oewn-poignant__5.00.00.moving.01"}],
  "oewn-toothless__3.00.00.." : [{"relType":"antonym","synset":"oewn-02447550-a","sense":"oewn-toothed__3.00.00.."}],
  "oewn-rosiness__1.07.01.." : [{"relType":"derivation","synset":"oewn-00372673-s","sense":"oewn-rosy__5.00.00.chromatic.00"}],
  "oewn-hermit__1.18.00.." : [{"relType":"derivation","synset":"oewn-02588984-s","sense":"oewn-hermitic__5.00.00.unworldly.00"},{"relType":"derivation","synset":"oewn-02588984-s","sense":"oewn-hermitical__5.00.00.unworldly.00"}],
  "oewn-biological__3.00.00.." : [{"relType":"antonym","synset":"oewn-01409235-a","sense":"oewn-adoptive__3.00.00.."}],
  "oewn-still__3.00.00.." : [{"relType":"antonym","synset":"oewn-02285028-a","sense":"oewn-sparkling__3.00.00.."}],
  "oewn-unipolar__3.00.00.." : [{"relType":"antonym","synset":"oewn-02485079-a","sense":"oewn-bipolar__3.00.00.."}],
  "oewn-spiritedness__1.07.00.." : [{"relType":"derivation","synset":"oewn-02286688-a","sense":"oewn-spirited__3.00.00.."},{"relType":"derivation","synset":"oewn-00808879-s","sense":"oewn-spirited__5.00.00.lively.00"},{"relType":"derivation","synset":"oewn-00119655-s","sense":"oewn-spirited__5.00.00.animated.00"}],
  "oewn-inhere__2.42.00.." : [{"relType":"derivation","synset":"oewn-01351376-s","sense":"oewn-inherent__5.00.00.intrinsic.00"},{"relType":"derivation","synset":"oewn-00945209-s","sense":"oewn-inherent__5.00.00.implicit.00"},{"relType":"derivation","synset":"oewn-13981424-n","sense":"oewn-inherence__1.26.00.."}],
  "oewn-imaginativeness__1.09.00.." : [{"relType":"derivation","synset":"oewn-00646885-s","sense":"oewn-imaginative__5.00.00.creative.00"}],
  "oewn-sentient__3.00.00.." : [{"relType":"antonym","synset":"oewn-00118565-a","sense":"oewn-insentient__3.00.00.."},{"relType":"derivation","synset":"oewn-05685793-n","sense":"oewn-sentience__1.09.01.."}],
  "oewn-tweed__1.06.00.." : [{"relType":"derivation","synset":"oewn-02248539-s","sense":"oewn-tweedy__5.00.00.rough.00"}],
  "oewn-straggle__1.14.00.." : [{"relType":"derivation","synset":"oewn-02435464-s","sense":"oewn-straggly__5.00.00.untidy.00"},{"relType":"derivation","synset":"oewn-02070232-v","sense":"oewn-straggle__2.38.00.."},{"relType":"derivation","synset":"oewn-02036072-v","sense":"oewn-straggle__2.38.01.."}],
  "oewn-short-spurred__3.00.00.." : [{"relType":"antonym","synset":"oewn-02606537-a","sense":"oewn-long-spurred__3.00.00.."}],
  "oewn-obliterate__2.30.02.." : [{"relType":"derivation","synset":"oewn-00901425-s","sense":"oewn-obliterable__5.00.00.eradicable.00"},{"relType":"derivation","synset":"oewn-07345613-n","sense":"oewn-obliteration__1.11.00.."}],
  "oewn-warm__3.00.02.." : [{"relType":"antonym","synset":"oewn-02541827-a","sense":"oewn-cool__3.00.02.."},{"relType":"derivation","synset":"oewn-07560035-n","sense":"oewn-warmness__1.12.00.."},{"relType":"pertainym","synset":"oewn-00221335-r","sense":"oewn-warmly__4.02.00.."}],
  "oewn-attendance__1.14.00.." : [{"relType":"derivation","synset":"oewn-01852738-s","sense":"oewn-attendant__5.00.00.present.02"}],
  "oewn-incommutable__3.00.00.." : [{"relType":"antonym","synset":"oewn-00349300-a","sense":"oewn-commutable__3.00.00.."}],
  "oewn-trimness__1.26.00.." : [{"relType":"derivation","synset":"oewn-00994531-s","sense":"oewn-trim__5.00.00.thin.03"},{"relType":"derivation","synset":"oewn-02432422-s","sense":"oewn-trim__5.00.01.tidy.00"},{"relType":"derivation","synset":"oewn-02431847-s","sense":"oewn-trim__5.00.02.tidy.00"}],
  "oewn-unrewarding__3.00.00.." : [{"relType":"antonym","synset":"oewn-02022785-a","sense":"oewn-rewarding__3.00.00.."}],
  "oewn-unproductive__3.00.00.." : [{"relType":"antonym","synset":"oewn-01871147-a","sense":"oewn-productive__3.00.00.."},{"relType":"derivation","synset":"oewn-05155786-n","sense":"oewn-unproductiveness__1.07.00.."},{"relType":"pertainym","synset":"oewn-00215382-r","sense":"oewn-unproductively__4.02.00.."}],
  "oewn-downhearted__5.00.00.dejected.00" : [{"relType":"derivation","synset":"oewn-07553056-n","sense":"oewn-downheartedness__1.12.00.."}],
  "oewn-gall__2.37.00.." : [{"relType":"derivation","synset":"oewn-07564444-n","sense":"oewn-gall__1.12.00.."}],
  "oewn-self-important__5.00.00.proud.00" : [{"relType":"derivation","synset":"oewn-07524045-n","sense":"oewn-self-importance__1.12.00.."},{"relType":"derivation","synset":"oewn-04894692-n","sense":"oewn-self-importance__1.07.00.."}],
  "oewn-rejoice__2.37.00.." : [{"relType":"derivation","synset":"oewn-07544951-n","sense":"oewn-rejoicing__1.12.00.."}],
  "oewn-ingratitude__1.12.00.." : [{"relType":"antonym","synset":"oewn-07519582-n","sense":"oewn-gratitude__1.12.00.."}],
  "oewn-heartless__3.00.02.." : [{"relType":"derivation","synset":"oewn-07521388-n","sense":"oewn-heartlessness__1.12.00.."},{"relType":"pertainym","synset":"oewn-00356954-r","sense":"oewn-heartlessly__4.02.00.."}],
  "oewn-rat__2.41.00.." : [{"relType":"derivation","synset":"oewn-10559272-n","sense":"oewn-rat__1.18.00.."},{"relType":"derivation","synset":"oewn-10026763-n","sense":"oewn-ratter__1.18.00.."}],
  "oewn-trip__2.34.00.." : [{"relType":"derivation","synset":"oewn-14401716-n","sense":"oewn-trip__1.26.00.."}],
  "oewn-sign__2.32.01.." : [{"relType":"derivation","synset":"oewn-06804229-n","sense":"oewn-sign__1.10.03.."},{"relType":"derivation","synset":"oewn-06889194-n","sense":"oewn-sign__1.10.01.."},{"relType":"derivation","synset":"oewn-10616913-n","sense":"oewn-signer__1.18.01.."},{"relType":"derivation","synset":"oewn-06888747-n","sense":"oewn-signing__1.10.00.."}],
  "oewn-cornice__2.40.00.." : [{"relType":"derivation","synset":"oewn-03115947-n","sense":"oewn-cornice__1.06.02.."},{"relType":"derivation","synset":"oewn-03115692-n","sense":"oewn-cornice__1.06.00.."}],
  "oewn-reverse__5.00.02.backward.01" : [{"relType":"derivation","synset":"oewn-13880801-n","sense":"oewn-reverse__1.24.00.."},{"relType":"derivation","synset":"oewn-00347519-n","sense":"oewn-reverse__1.04.01.."}],
  "oewn-gelatinize__2.30.01.." : [{"relType":"derivation","synset":"oewn-14754732-n","sense":"oewn-gelatin__1.27.00.."}],
  "oewn-membranous__5.00.00.unhealthy.00" : [{"relType":"derivation","synset":"oewn-05433820-n","sense":"oewn-membrane__1.08.00.."}],
  "oewn-cauterise__2.30.00.." : [{"relType":"derivation","synset":"oewn-02990502-n","sense":"oewn-cautery__1.06.00.."},{"relType":"derivation","synset":"oewn-00669355-n","sense":"oewn-cautery__1.04.00.."},{"relType":"derivation","synset":"oewn-00669355-n","sense":"oewn-cauterisation__1.04.00.."}],
  "oewn-sprinkle__2.30.00.." : [{"relType":"derivation","synset":"oewn-04296165-n","sense":"oewn-sprinkler__1.06.00.."},{"relType":"derivation","synset":"oewn-00279399-n","sense":"oewn-sprinkle__1.04.00.."},{"relType":"derivation","synset":"oewn-00279399-n","sense":"oewn-sprinkling__1.04.02.."}],
  "oewn-harpist__1.18.00.." : [{"relType":"derivation","synset":"oewn-03500383-n","sense":"oewn-harp__1.06.00.."},{"relType":"derivation","synset":"oewn-03499379-n","sense":"oewn-harp__1.06.02.."}],
  "oewn-capsulate__2.35.00.." : [{"relType":"derivation","synset":"oewn-02961022-n","sense":"oewn-capsule__1.06.00.."}],
  "oewn-arrest__2.38.00.." : [{"relType":"derivation","synset":"oewn-02745473-n","sense":"oewn-arrester__1.06.00.."}],
  "oewn-check_out__2.40.00.." : [{"relType":"derivation","synset":"oewn-03015395-n","sense":"oewn-checkout__1.06.00.."}],
  "oewn-fence__2.35.00.." : [{"relType":"derivation","synset":"oewn-03332179-n","sense":"oewn-fence__1.06.00.."},{"relType":"derivation","synset":"oewn-03332179-n","sense":"oewn-fencing__1.06.00.."}],
  "oewn-prosthetist__1.18.00.." : [{"relType":"derivation","synset":"oewn-04020105-n","sense":"oewn-prosthesis__1.06.00.."}],
  "oewn-objective__5.00.00.real.00" : [{"relType":"derivation","synset":"oewn-04899539-n","sense":"oewn-objectivity__1.07.00.."},{"relType":"derivation","synset":"oewn-04899539-n","sense":"oewn-objectiveness__1.07.00.."}],
  "oewn-voice__2.32.01.." : [{"relType":"derivation","synset":"oewn-07125323-n","sense":"oewn-voice__1.10.00.."},{"relType":"derivation","synset":"oewn-05209552-n","sense":"oewn-voice__1.07.01.."},{"relType":"antonym","synset":"oewn-00952702-v","sense":"oewn-devoice__2.32.00.."}],
  "oewn-recommend__2.32.01.." : [{"relType":"derivation","synset":"oewn-06684382-n","sense":"oewn-recommendation__1.10.00.."}],
  "oewn-sciolistic__5.00.00.superficial.00" : [{"relType":"derivation","synset":"oewn-05102823-n","sense":"oewn-sciolism__1.07.00.."}],
  "oewn-bottomless__5.00.00.unlimited.00" : [{"relType":"derivation","synset":"oewn-05142847-n","sense":"oewn-bottomlessness__1.07.00.."}],
  "oewn-distasteful__5.00.00.unpalatable.00" : [{"relType":"derivation","synset":"oewn-05003736-n","sense":"oewn-distastefulness__1.07.01.."}],
  "oewn-variegate__2.30.00.." : [{"relType":"derivation","synset":"oewn-00196418-n","sense":"oewn-variegation__1.04.00.."}],
  "oewn-runny__5.00.00.liquid.00" : [{"relType":"derivation","synset":"oewn-07422377-n","sense":"oewn-run__1.11.00.."},{"relType":"derivation","synset":"oewn-04944220-n","sense":"oewn-runniness__1.07.00.."}],
  "oewn-lofty__5.00.00.impressive.00" : [{"relType":"derivation","synset":"oewn-04737242-n","sense":"oewn-loftiness__1.07.02.."}],
  "oewn-sweet__5.00.02.pleasing.00" : [{"relType":"derivation","synset":"oewn-04785869-n","sense":"oewn-sweetness__1.07.03.."}],
  "oewn-precedential__5.00.00.senior.00" : [{"relType":"derivation","synset":"oewn-13973020-n","sense":"oewn-precedence__1.26.00.."}],
  "oewn-teacher__1.18.00.." : [{"relType":"derivation","synset":"oewn-00605926-n","sense":"oewn-teachership__1.04.00.."},{"relType":"derivation","synset":"oewn-00830768-v","sense":"oewn-teach__2.32.00.."},{"relType":"derivation","synset":"oewn-00274533-v","sense":"oewn-teach__2.30.00.."}],
  "oewn-speech_therapist__1.18.00.." : [{"relType":"derivation","synset":"oewn-00708466-n","sense":"oewn-speech_therapy__1.04.00.."}],
  "oewn-campaign__2.33.01.." : [{"relType":"derivation","synset":"oewn-07488069-n","sense":"oewn-campaign__1.11.00.."},{"relType":"derivation","synset":"oewn-09909143-n","sense":"oewn-campaigner__1.18.00.."}],
  "oewn-desecrate__2.41.00.." : [{"relType":"derivation","synset":"oewn-00747885-n","sense":"oewn-desecration__1.04.00.."}],
  "oewn-transmute__2.30.02.." : [{"relType":"derivation","synset":"oewn-01253413-n","sense":"oewn-transmutation__1.04.00.."}],
  "oewn-segregate__2.30.00.." : [{"relType":"derivation","synset":"oewn-01204674-n","sense":"oewn-segregation__1.04.00.."}],
  "oewn-debunk__2.32.00.." : [{"relType":"derivation","synset":"oewn-00523394-n","sense":"oewn-debunking__1.04.00.."}],
  "oewn-superintend__2.41.00.." : [{"relType":"derivation","synset":"oewn-01137850-n","sense":"oewn-superintendence__1.04.00.."},{"relType":"derivation","synset":"oewn-10408431-n","sense":"oewn-superintendent__1.18.00.."}],
  "oewn-humanise__2.37.00.." : [{"relType":"derivation","synset":"oewn-00265618-n","sense":"oewn-humanisation__1.04.00.."}],
  "oewn-decompress__2.35.00.." : [{"relType":"derivation","synset":"oewn-00617881-n","sense":"oewn-decompression__1.04.01.."},{"relType":"antonym","synset":"oewn-01391983-v","sense":"oewn-compress__2.35.01.."}],
  "oewn-perform__2.36.00.." : [{"relType":"derivation","synset":"oewn-00098324-n","sense":"oewn-performance__1.04.00.."}],
  "oewn-reactionary__5.00.00.right.03" : [{"relType":"derivation","synset":"oewn-06226571-n","sense":"oewn-reaction__1.09.01.."},{"relType":"derivation","synset":"oewn-10528068-n","sense":"oewn-reactionary__1.18.00.."}],
  "oewn-freeze__2.30.01.." : [{"relType":"derivation","synset":"oewn-01065621-n","sense":"oewn-freeze__1.04.01.."}],
  "oewn-kick_off__2.41.00.." : [{"relType":"derivation","synset":"oewn-15290329-n","sense":"oewn-kickoff__1.28.00.."},{"relType":"derivation","synset":"oewn-07344168-n","sense":"oewn-kickoff__1.11.00.."}],
  "oewn-pursue__2.41.00.." : [{"relType":"derivation","synset":"oewn-00432492-n","sense":"oewn-pursuit__1.04.01.."},{"relType":"derivation","synset":"oewn-10514752-n","sense":"oewn-pursuer__1.18.01.."}],
  "oewn-roost__1.06.00.." : [{"relType":"derivation","synset":"oewn-01546513-v","sense":"oewn-roost__2.35.00.."}],
  "oewn-grounding__1.04.00.." : [{"relType":"derivation","synset":"oewn-01295137-v","sense":"oewn-ground__2.35.02.."}],
  "oewn-attach_to__2.42.00.." : [{"relType":"also","synset":"oewn-01292858-v","sense":"oewn-attach__2.35.02.."}],
  "oewn-pickings__1.04.00.." : [{"relType":"derivation","synset":"oewn-02326628-v","sense":"oewn-pick__2.40.01.."}],
  "oewn-dipper__1.06.00.." : [{"relType":"derivation","synset":"oewn-01579924-v","sense":"oewn-dip__2.35.00.."},{"relType":"derivation","synset":"oewn-01194845-v","sense":"oewn-dip__2.34.00.."}],
  "oewn-fish__1.13.00.." : [{"relType":"derivation","synset":"oewn-01143220-v","sense":"oewn-fish__2.33.00.."}],
  "oewn-withdrawer__1.18.03.." : [{"relType":"derivation","synset":"oewn-01514012-v","sense":"oewn-withdraw__2.35.00.."}],
  "oewn-fence__1.06.00.." : [{"relType":"derivation","synset":"oewn-01591055-v","sense":"oewn-fence__2.35.00.."},{"relType":"derivation","synset":"oewn-01133033-v","sense":"oewn-fence__2.33.00.."}],
  "oewn-unsaddle__2.35.00.." : [{"relType":"antonym","synset":"oewn-01495079-v","sense":"oewn-saddle__2.35.01.."}],
  "oewn-abrasion__1.22.00.." : [{"relType":"derivation","synset":"oewn-01256577-v","sense":"oewn-abrade__2.35.00.."}],
  "oewn-clamp__1.06.00.." : [{"relType":"derivation","synset":"oewn-01346292-v","sense":"oewn-clamp__2.35.00.."}],
  "oewn-love__1.04.00.." : [{"relType":"derivation","synset":"oewn-01429048-v","sense":"oewn-love__2.35.00.."}],
  "oewn-exclusive__5.00.00.unshared.00" : [{"relType":"derivation","synset":"oewn-00617464-v","sense":"oewn-exclude__2.31.01.."},{"relType":"pertainym","synset":"oewn-00009062-r","sense":"oewn-exclusively__4.02.00.."}],
  "oewn-reabsorption__1.22.00.." : [{"relType":"derivation","synset":"oewn-01542701-v","sense":"oewn-reabsorb__2.35.00.."}],
  "oewn-absorption__1.09.00.." : [{"relType":"derivation","synset":"oewn-00601765-v","sense":"oewn-absorb__2.31.03.."}],
  "oewn-pervasion__1.22.00.." : [{"relType":"derivation","synset":"oewn-01231635-v","sense":"oewn-pervade__2.35.00.."}],
  "oewn-swim__1.04.00.." : [{"relType":"derivation","synset":"oewn-01964770-v","sense":"oewn-swim__2.38.00.."},{"relType":"derivation","synset":"oewn-01908286-v","sense":"oewn-swim__2.38.01.."}],
  "oewn-answerer__1.18.00.." : [{"relType":"derivation","synset":"oewn-00817348-v","sense":"oewn-answer__2.32.00.."}],
  "oewn-unify__2.35.00.." : [{"relType":"derivation","synset":"oewn-00003553-n","sense":"oewn-unit__1.03.00.."}],
  "oewn-huxleian__3.01.00.." : [{"relType":"derivation","synset":"oewn-11089524-n","sense":"oewn-huxley__1.18.00.."}],
  "oewn-archaeology__1.09.00.." : [{"relType":"derivation","synset":"oewn-09824229-n","sense":"oewn-archaeologist__1.18.00.."},{"relType":"derivation","synset":"oewn-02649043-a","sense":"oewn-archaeologic__3.01.00.."},{"relType":"derivation","synset":"oewn-02649043-a","sense":"oewn-archaeological__3.01.00.."}],
  "oewn-sit__2.41.05.." : [{"relType":"derivation","synset":"oewn-09848551-n","sense":"oewn-sitter__1.18.00.."}],
  "oewn-pretend__2.36.00.." : [{"relType":"derivation","synset":"oewn-10221154-n","sense":"oewn-pretender__1.18.00.."}],
  "oewn-proconsular__3.01.00.." : [{"relType":"derivation","synset":"oewn-10498047-n","sense":"oewn-proconsul__1.18.02.."},{"relType":"derivation","synset":"oewn-10497878-n","sense":"oewn-proconsul__1.18.00.."}],
  "oewn-friend__1.18.03.." : [{"relType":"antonym","synset":"oewn-10118479-n","sense":"oewn-foe__1.18.00.."}],
  "oewn-freudian__3.01.00.." : [{"relType":"derivation","synset":"oewn-11002123-n","sense":"oewn-freud__1.18.00.."}],
  "oewn-hew__2.35.02.." : [{"relType":"derivation","synset":"oewn-10193779-n","sense":"oewn-hewer__1.18.00.."}],
  "oewn-fijian__3.01.00.." : [{"relType":"derivation","synset":"oewn-09725305-n","sense":"oewn-fijian__1.18.00.."},{"relType":"derivation","synset":"oewn-06951400-n","sense":"oewn-fijian__1.10.00.."},{"relType":"derivation","synset":"oewn-08797001-n","sense":"oewn-fiji__1.15.00.."}],
  "oewn-upstage__2.38.00.." : [{"relType":"derivation","synset":"oewn-10760389-n","sense":"oewn-upstager__1.18.00.."}],
  "oewn-totter__2.38.01.." : [{"relType":"derivation","synset":"oewn-10665293-n","sense":"oewn-totterer__1.18.00.."}],
  "oewn-apostolical__3.01.00.." : [{"relType":"derivation","synset":"oewn-09818234-n","sense":"oewn-apostle__1.18.00.."}],
  "oewn-bread__2.35.00.." : [{"relType":"derivation","synset":"oewn-07695101-n","sense":"oewn-bread__1.13.00.."}],
  "oewn-bilabial__3.01.00.." : [{"relType":"derivation","synset":"oewn-07132041-n","sense":"oewn-bilabial__1.10.00.."}],
  "oewn-conspire__2.31.01.." : [{"relType":"derivation","synset":"oewn-06536926-n","sense":"oewn-conspiracy__1.10.00.."},{"relType":"derivation","synset":"oewn-02930588-a","sense":"oewn-conspirative__3.01.00.."}],
  "oewn-purport__2.31.00.." : [{"relType":"derivation","synset":"oewn-06618250-n","sense":"oewn-purport__1.10.00.."}],
  "oewn-meteorologic__3.01.00.." : [{"relType":"derivation","synset":"oewn-06128170-n","sense":"oewn-meteorology__1.09.00.."},{"relType":"pertainym","synset":"oewn-00135104-r","sense":"oewn-meteorologically__4.02.00.."}],
  "oewn-visken__1.06.00.." : [{"relType":"is_exemplified_by","synset":"oewn-06858649-n","sense":"oewn-trade_name__1.10.00.."}],
  "oewn-skiing__1.04.00.." : [{"relType":"derivation","synset":"oewn-01942285-v","sense":"oewn-ski__2.38.00.."}],
  "oewn-drain__1.04.01.." : [{"relType":"derivation","synset":"oewn-01160320-v","sense":"oewn-drain__2.34.00.."}],
  "oewn-retroflexion__1.10.00.." : [{"relType":"derivation","synset":"oewn-00981443-v","sense":"oewn-retroflex__2.32.00.."}],
  "oewn-jig__1.10.00.." : [{"relType":"derivation","synset":"oewn-01902025-v","sense":"oewn-jig__2.38.00.."}],
  "oewn-arch__1.06.00.." : [{"relType":"derivation","synset":"oewn-02038831-v","sense":"oewn-arch__2.38.00.."},{"relType":"pertainym","synset":"oewn-02649715-a","sense":"oewn-arched__3.01.00.."}],
  "oewn-traveling__1.04.00.." : [{"relType":"derivation","synset":"oewn-01849662-v","sense":"oewn-travel__2.38.04.."}],
  "oewn-pioneer__1.18.01.." : [{"relType":"derivation","synset":"oewn-01648963-v","sense":"oewn-pioneer__2.36.00.."},{"relType":"derivation","synset":"oewn-01645456-v","sense":"oewn-pioneer__2.36.01.."}],
  "oewn-standardization__1.04.01.." : [{"relType":"derivation","synset":"oewn-00684355-v","sense":"oewn-standardize__2.31.00.."}],
  "oewn-surmise__1.10.00.." : [{"relType":"derivation","synset":"oewn-00690947-v","sense":"oewn-surmise__2.31.00.."},{"relType":"derivation","synset":"oewn-00923043-v","sense":"oewn-surmise__2.32.00.."}],
  "oewn-naturalist__1.18.01.." : [{"relType":"derivation","synset":"oewn-05982239-n","sense":"oewn-naturalism__1.09.00.."}],
  "oewn-cacogenic__3.01.00.." : [{"relType":"derivation","synset":"oewn-06052221-n","sense":"oewn-cacogenics__1.09.00.."}],
  "oewn-commune__1.14.00.." : [{"relType":"derivation","synset":"oewn-00410206-v","sense":"oewn-communise__2.30.01.."},{"relType":"derivation","synset":"oewn-00409777-v","sense":"oewn-communise__2.30.00.."}],
  "oewn-buttress__1.06.00.." : [{"relType":"derivation","synset":"oewn-00223287-v","sense":"oewn-buttress__2.30.01.."}],
  "oewn-american__1.18.00.." : [{"relType":"derivation","synset":"oewn-00411331-v","sense":"oewn-americanize__2.30.01.."},{"relType":"derivation","synset":"oewn-02938825-a","sense":"oewn-american__3.01.01.."}],
  "oewn-putrefactive__5.00.00.septic.00" : [{"relType":"derivation","synset":"oewn-00400459-v","sense":"oewn-putrefy__2.30.00.."}],
  "oewn-fracture__1.04.00.." : [{"relType":"derivation","synset":"oewn-00336176-v","sense":"oewn-fracture__2.30.10.."},{"relType":"derivation","synset":"oewn-00107747-v","sense":"oewn-fracture__2.29.01.."},{"relType":"derivation","synset":"oewn-00107543-v","sense":"oewn-fracture__2.29.00.."}],
  "oewn-closure__1.10.00.." : [{"relType":"derivation","synset":"oewn-00528114-v","sense":"oewn-closure__2.30.00.."}],
  "oewn-impairment__1.04.00.." : [{"relType":"derivation","synset":"oewn-00478872-v","sense":"oewn-impair__2.30.01.."}],
  "oewn-opal__1.27.00.." : [{"relType":"derivation","synset":"oewn-00117038-v","sense":"oewn-opalize__2.30.01.."},{"relType":"derivation","synset":"oewn-00116893-v","sense":"oewn-opalize__2.30.00.."}],
  "oewn-commitment__1.04.00.." : [{"relType":"derivation","synset":"oewn-00888984-v","sense":"oewn-commit__2.32.01.."}],
  "oewn-coercive__5.00.00.powerful.00" : [{"relType":"derivation","synset":"oewn-02510211-v","sense":"oewn-coerce__2.41.00.."}],
  "oewn-venture__1.04.00.." : [{"relType":"derivation","synset":"oewn-02378427-v","sense":"oewn-venture__2.41.01.."}],
  "oewn-slave__1.18.01.." : [{"relType":"derivation","synset":"oewn-02426299-v","sense":"oewn-slave__2.41.00.."}],
  "oewn-certifiable__5.00.00.insane.00" : [{"relType":"derivation","synset":"oewn-00823923-v","sense":"oewn-certify__2.32.01.."}],
  "oewn-embarrassment__1.11.00.." : [{"relType":"derivation","synset":"oewn-01796126-v","sense":"oewn-embarrass__2.37.00.."},{"relType":"antonym","synset":"oewn-07320378-n","sense":"oewn-disembarrassment__1.11.00.."}],
  "oewn-farming__1.04.00.." : [{"relType":"derivation","synset":"oewn-01743695-v","sense":"oewn-farm__2.36.00.."}],
  "oewn-myriad__5.00.00.incalculable.00" : [{"relType":"derivation","synset":"oewn-13798938-n","sense":"oewn-myriad__1.23.01.."}],
  "oewn-pair__2.35.04.." : [{"relType":"derivation","synset":"oewn-08001665-n","sense":"oewn-pair__1.14.01.."},{"relType":"derivation","synset":"oewn-13765745-n","sense":"oewn-pair__1.23.00.."}],
  "oewn-titillation__1.04.01.." : [{"relType":"derivation","synset":"oewn-01820186-v","sense":"oewn-titillate__2.37.00.."}],
  "oewn-aquatint__1.06.00.." : [{"relType":"derivation","synset":"oewn-01754476-v","sense":"oewn-aquatint__2.36.00.."}],
  "oewn-anthracitic__3.01.00.." : [{"relType":"derivation","synset":"oewn-14839091-n","sense":"oewn-anthracite__1.27.00.."}],
  "oewn-bolivian__3.01.00.." : [{"relType":"derivation","synset":"oewn-08871835-n","sense":"oewn-bolivia__1.15.00.."}],
  "oewn-hominid__5.00.00.human.00" : [{"relType":"derivation","synset":"oewn-02474393-n","sense":"oewn-hominid__1.05.00.."}],
  "oewn-hymenopterous__3.01.00.." : [{"relType":"derivation","synset":"oewn-02208548-n","sense":"oewn-hymenoptera__1.05.00.."}],
  "oewn-ferny__3.00.01.." : [{"relType":"derivation","synset":"oewn-11566165-n","sense":"oewn-fern__1.20.00.."}],
  "oewn-epochal__5.00.00.significant.00" : [{"relType":"derivation","synset":"oewn-15273375-n","sense":"oewn-epoch__1.28.00.."}],
  "oewn-paroxysm__1.26.00.." : [{"relType":"derivation","synset":"oewn-02785611-a","sense":"oewn-paroxysmal__3.01.00.."},{"relType":"pertainym","synset":"oewn-02785611-a","sense":"oewn-paroxysmal__3.01.00.."}],
  "oewn-ghana__1.15.00.." : [{"relType":"pertainym","synset":"oewn-03079901-a","sense":"oewn-ghanese__3.01.00.."},{"relType":"derivation","synset":"oewn-03079901-a","sense":"oewn-ghanaian__3.01.00.."},{"relType":"pertainym","synset":"oewn-03079901-a","sense":"oewn-ghanaian__3.01.00.."},{"relType":"derivation","synset":"oewn-03079901-a","sense":"oewn-ghanian__3.01.00.."},{"relType":"pertainym","synset":"oewn-03079901-a","sense":"oewn-ghanian__3.01.00.."}],
  "oewn-entropy__1.07.00.." : [{"relType":"pertainym","synset":"oewn-02762661-a","sense":"oewn-isentropic__3.01.00.."}],
  "oewn-bungalow__1.06.00.." : [{"relType":"pertainym","synset":"oewn-03062917-a","sense":"oewn-bungaloid__3.01.00.."}],
  "oewn-kashmiri__1.10.00.." : [{"relType":"derivation","synset":"oewn-03089662-a","sense":"oewn-kashmiri__3.01.00.."}],
  "oewn-mozambique__1.15.00.." : [{"relType":"derivation","synset":"oewn-03100016-a","sense":"oewn-mozambican__3.01.01.."},{"relType":"pertainym","synset":"oewn-03100016-a","sense":"oewn-mozambican__3.01.01.."},{"relType":"derivation","synset":"oewn-03099842-a","sense":"oewn-mozambican__3.01.00.."}],
  "oewn-interface__1.06.00.." : [{"relType":"derivation","synset":"oewn-02889984-a","sense":"oewn-interfacial__3.01.00.."},{"relType":"pertainym","synset":"oewn-02889984-a","sense":"oewn-interfacial__3.01.00.."}],
  "oewn-moroccan__1.18.00.." : [{"relType":"derivation","synset":"oewn-03035934-a","sense":"oewn-moroccan__3.01.00.."}],
  "oewn-loyally__4.02.00.." : [{"relType":"antonym","synset":"oewn-00317712-r","sense":"oewn-disloyally__4.02.00.."}],
  "oewn-philanthropic__5.00.00.charitable.00" : [{"relType":"pertainym","synset":"oewn-00423660-r","sense":"oewn-philanthropically__4.02.00.."}],
  "oewn-didactic__5.00.00.instructive.00" : [{"relType":"pertainym","synset":"oewn-00313044-r","sense":"oewn-didactically__4.02.00.."}],
  "oewn-dropsical__5.00.00.unhealthy.00" : [{"relType":"derivation","synset":"oewn-14340141-n","sense":"oewn-dropsy__1.26.00.."}],
  "oewn-execration__1.09.00.." : [{"relType":"derivation","synset":"oewn-01778347-v","sense":"oewn-execrate__2.37.00.."},{"relType":"derivation","synset":"oewn-00866574-v","sense":"oewn-execrate__2.32.00.."}],
  "oewn-comforter__1.18.01.." : [{"relType":"derivation","synset":"oewn-01818782-v","sense":"oewn-comfort__2.37.01.."}],
  "oewn-snack__1.13.00.." : [{"relType":"derivation","synset":"oewn-01175702-v","sense":"oewn-snack__2.34.00.."}],
  "oewn-radio__1.06.00.." : [{"relType":"derivation","synset":"oewn-01009522-v","sense":"oewn-radio__2.32.00.."}]
}