{
  "ewn-accommodate-v-00483824-01" : [{"relType":"derivation","synset":"ewn-07384204-n","sense":"ewn-accommodation-n-07384204-02"},{"relType":"derivation","synset":"ewn-07192097-n","sense":"ewn-accommodation-n-07192097-01"},{"relType":"derivation","synset":"ewn-05763483-n","sense":"ewn-accommodation-n-05763483-01"}],
  "ewn-read-v-00628065-01" : [{"relType":"derivation","synset":"ewn-07249541-n","sense":"ewn-reading-n-07249541-03"},{"relType":"derivation","synset":"ewn-10528303-n","sense":"ewn-reader-n-10528303-01"},{"relType":"derivation","synset":"ewn-10528455-n","sense":"ewn-reader-n-10528455-01"}],
  "ewn-middle-n-05876894-01" : [{"relType":"antonym","synset":"ewn-05876673-n","sense":"ewn-beginning-n-05876673-01"},{"relType":"antonym","synset":"ewn-05877099-n","sense":"ewn-end-n-05877099-01"},{"relType":"derivation","synset":"ewn-01501137-v","sense":"ewn-middle-v-01501137-01"}],
  "ewn-paradisal-s-01183628-05" : [{"relType":"derivation","synset":"ewn-05636722-n","sense":"ewn-Paradise-n-05636722-01"},{"relType":"derivation","synset":"ewn-08583035-n","sense":"ewn-paradise-n-08583035-02"}],
  "ewn-presume-v-00633898-02" : [{"relType":"derivation","synset":"ewn-05901963-n","sense":"ewn-presumption-n-05901963-02"},{"relType":"derivation","synset":"ewn-05789344-n","sense":"ewn-presumption-n-05789344-01"},{"relType":"derivation","synset":"ewn-01228051-n","sense":"ewn-presumption-n-01228051-01"},{"relType":"derivation","synset":"ewn-01416413-s","sense":"ewn-presumptive-s-01416413-01"},{"relType":"derivation","synset":"ewn-00648303-s","sense":"ewn-presumptive-s-00648303-01"}],
  "ewn-radiochemist-n-10384201-02" : [{"relType":"derivation","synset":"ewn-06100128-n","sense":"ewn-radiochemistry-n-06100128-01"}],
  "ewn-dull-s-00395053-01" : [{"relType":"derivation","synset":"ewn-04962810-n","sense":"ewn-dullness-n-04962810-01"}],
  "ewn-colorize-v-00284671-02" : [{"relType":"derivation","synset":"ewn-04963771-n","sense":"ewn-color-n-04963771-01"}],
  "ewn-archaeologic-a-02649043-03" : [{"relType":"derivation","synset":"ewn-06153532-n","sense":"ewn-archaeology-n-06153532-02"}],
  "ewn-streetwalker-n-10682754-01" : [{"relType":"derivation","synset":"ewn-02559943-v","sense":"ewn-streetwalk-v-02559943-02"}],
  "ewn-bumper-n-02921979-01" : [{"relType":"derivation","synset":"ewn-01242183-v","sense":"ewn-bump-v-01242183-01"}],
  "ewn-grind-n-00359116-01" : [{"relType":"derivation","synset":"ewn-01597899-v","sense":"ewn-grind-v-01597899-04"},{"relType":"derivation","synset":"ewn-01397118-v","sense":"ewn-grind-v-01397118-02"},{"relType":"derivation","synset":"ewn-00331892-v","sense":"ewn-grind-v-00331892-01"}],
  "ewn-burglar-n-09900207-01" : [{"relType":"derivation","synset":"ewn-02577426-v","sense":"ewn-burglarise-v-02577426-02"}],
  "ewn-reaction-n-00860679-01" : [{"relType":"derivation","synset":"ewn-00719282-v","sense":"ewn-react-v-00719282-01"},{"relType":"pertainym","synset":"ewn-02905688-a","sense":"ewn-sensorimotor-a-02905688-01"},{"relType":"pertainym","synset":"ewn-02925183-a","sense":"ewn-psychomotor-a-02925183-01"}],
  "ewn-mess-up-n-00076438-04" : [{"relType":"derivation","synset":"ewn-02533317-v","sense":"ewn-mess_up-v-02533317-23"}],
  "ewn-mismanagement-n-01136800-01" : [{"relType":"derivation","synset":"ewn-02443726-v","sense":"ewn-mismanage-v-02443726-01"}],
  "ewn-exit-v-02019450-01" : [{"relType":"antonym","synset":"ewn-02020375-v","sense":"ewn-enter-v-02020375-01"},{"relType":"derivation","synset":"ewn-03308910-n","sense":"ewn-exit-n-03308910-01"},{"relType":"derivation","synset":"ewn-00059339-n","sense":"ewn-exit-n-00059339-01"}],
  "ewn-hanging-n-01019643-03" : [{"relType":"derivation","synset":"ewn-01484587-v","sense":"ewn-hang-v-01484587-01"}],
  "ewn-specialiser-n-10651303-03" : [{"relType":"derivation","synset":"ewn-02451029-v","sense":"ewn-specialise-v-02451029-02"}],
  "ewn-passing-n-00867278-02" : [{"relType":"derivation","synset":"ewn-00072742-v","sense":"ewn-pass-v-00072742-04"}],
  "ewn-paddle-n-03879252-01" : [{"relType":"derivation","synset":"ewn-01423582-v","sense":"ewn-paddle-v-01423582-02"}],
  "ewn-shut_up-v-01350360-05" : [{"relType":"also","synset":"ewn-01347791-v","sense":"ewn-shut-v-01347791-02"},{"relType":"also","synset":"ewn-01347791-v","sense":"ewn-shut-v-01347791-02"}],
  "ewn-reenactor-n-10533714-01" : [{"relType":"derivation","synset":"ewn-01726692-v","sense":"ewn-reenact-v-01726692-01"}],
  "ewn-helper-n-09631739-02" : [{"relType":"derivation","synset":"ewn-02553283-v","sense":"ewn-help-v-02553283-01"},{"relType":"derivation","synset":"ewn-02561142-v","sense":"ewn-help-v-02561142-01"}],
  "ewn-realization-n-00933662-01" : [{"relType":"derivation","synset":"ewn-01648288-v","sense":"ewn-realize-v-01648288-01"}],
  "ewn-lose-v-02292463-01" : [{"relType":"antonym","synset":"ewn-02290474-v","sense":"ewn-find-v-02290474-01"},{"relType":"derivation","synset":"ewn-13350344-n","sense":"ewn-losings-n-13350344-01"}],
  "ewn-preserve-n-08604994-01" : [{"relType":"derivation","synset":"ewn-02738997-v","sense":"ewn-preserve-v-02738997-02"}],
  "ewn-victualler-n-10772850-02" : [{"relType":"derivation","synset":"ewn-02337995-v","sense":"ewn-victual-v-02337995-01"}],
  "ewn-takeaway-n-07610082-03" : [{"relType":"derivation","synset":"ewn-01169274-v","sense":"ewn-take_away-v-01169274-02"}],
  "ewn-creditor-n-09996258-01" : [{"relType":"derivation","synset":"ewn-02269560-v","sense":"ewn-credit-v-02269560-01"},{"relType":"antonym","synset":"ewn-10017160-n","sense":"ewn-debtor-n-10017160-01"}],
  "ewn-top-n-08635538-04" : [{"relType":"derivation","synset":"ewn-02085425-v","sense":"ewn-top-v-02085425-02"},{"relType":"derivation","synset":"ewn-02025228-v","sense":"ewn-top-v-02025228-01"}],
  "ewn-discoverer-n-10234307-02" : [{"relType":"derivation","synset":"ewn-01641524-v","sense":"ewn-discover-v-01641524-01"}],
  "ewn-roller-n-04108795-01" : [{"relType":"derivation","synset":"ewn-01870178-v","sense":"ewn-roll-v-01870178-01"}],
  "ewn-cortical-a-02986524-01" : [{"relType":"pertainym","synset":"ewn-00094168-r","sense":"ewn-cortically-r-00094168-01"},{"relType":"derivation","synset":"ewn-05494162-n","sense":"ewn-cortex-n-05494162-04"},{"relType":"derivation","synset":"ewn-05498230-n","sense":"ewn-cortex-n-05498230-01"},{"relType":"pertainym","synset":"ewn-02994388-a","sense":"ewn-thalamocortical-a-02994388-01"}],
  "ewn-abaxial-a-00002312-01" : [{"relType":"pertainym","synset":"ewn-00515036-r","sense":"ewn-abaxially-r-00515036-01"},{"relType":"antonym","synset":"ewn-00002527-a","sense":"ewn-adaxial-a-00002527-01"}],
  "ewn-truculent-s-00085264-01" : [{"relType":"pertainym","synset":"ewn-00483779-r","sense":"ewn-truculently-r-00483779-01"},{"relType":"derivation","synset":"ewn-04651518-n","sense":"ewn-truculence-n-04651518-01"},{"relType":"derivation","synset":"ewn-04651518-n","sense":"ewn-truculency-n-04651518-02"}],
  "ewn-unquestioning-s-00005598-02" : [{"relType":"pertainym","synset":"ewn-00504312-r","sense":"ewn-unquestioningly-r-00504312-01"}],
  "ewn-identifiable-a-01275507-01" : [{"relType":"pertainym","synset":"ewn-00363013-r","sense":"ewn-identifiably-r-00363013-01"},{"relType":"derivation","synset":"ewn-00620568-v","sense":"ewn-identify-v-00620568-01"},{"relType":"derivation","synset":"ewn-00654017-v","sense":"ewn-identify-v-00654017-01"},{"relType":"antonym","synset":"ewn-01276253-a","sense":"ewn-unidentifiable-a-01276253-01"}],
  "ewn-unpatriotically-r-00420451-01" : [{"relType":"antonym","synset":"ewn-00420302-r","sense":"ewn-patriotically-r-00420302-01"}],
  "ewn-noncomprehensive-a-00531280-01" : [{"relType":"pertainym","synset":"ewn-00289871-r","sense":"ewn-noncomprehensively-r-00289871-01"},{"relType":"antonym","synset":"ewn-00527630-a","sense":"ewn-comprehensive-a-00527630-01"}],
  "ewn-random-a-01930715-01" : [{"relType":"pertainym","synset":"ewn-00071165-r","sense":"ewn-randomly-r-00071165-01"},{"relType":"derivation","synset":"ewn-04778571-n","sense":"ewn-randomness-n-04778571-01"},{"relType":"antonym","synset":"ewn-01931557-a","sense":"ewn-nonrandom-a-01931557-01"}],
  "ewn-diffident-a-00340839-01" : [{"relType":"pertainym","synset":"ewn-00310504-r","sense":"ewn-diffidently-r-00310504-01"},{"relType":"derivation","synset":"ewn-07538525-n","sense":"ewn-diffidence-n-07538525-01"},{"relType":"antonym","synset":"ewn-00339715-a","sense":"ewn-confident-a-00339715-01"}],
  "ewn-unutterable-s-00947318-06" : [{"relType":"pertainym","synset":"ewn-00373649-r","sense":"ewn-unutterably-r-00373649-03"}],
  "ewn-incautious-a-00327334-01" : [{"relType":"pertainym","synset":"ewn-00283873-r","sense":"ewn-incautiously-r-00283873-01"},{"relType":"antonym","synset":"ewn-00326179-a","sense":"ewn-cautious-a-00326179-01"}],
  "ewn-federal-a-02736565-01" : [{"relType":"pertainym","synset":"ewn-00124703-r","sense":"ewn-federally-r-00124703-01"}],
  "ewn-illustrious-s-01125751-01" : [{"relType":"pertainym","synset":"ewn-00365674-r","sense":"ewn-illustriously-r-00365674-01"},{"relType":"derivation","synset":"ewn-05177128-n","sense":"ewn-illustriousness-n-05177128-02"}],
  "ewn-half-a-s-00519479-01" : [{"relType":"pertainym","synset":"ewn-00008300-r","sense":"ewn-half-r-00008300-01"}],
  "ewn-a_posteriori-r-00252994-01" : [{"relType":"antonym","synset":"ewn-00253080-r","sense":"ewn-a_priori-r-00253080-01"}],
  "ewn-intransitive-a-02498585-01" : [{"relType":"pertainym","synset":"ewn-00383087-r","sense":"ewn-intransitively-r-00383087-01"},{"relType":"derivation","synset":"ewn-13820513-n","sense":"ewn-intransitivity-n-13820513-01"},{"relType":"derivation","synset":"ewn-13820513-n","sense":"ewn-intransitiveness-n-13820513-02"},{"relType":"antonym","synset":"ewn-02498383-a","sense":"ewn-transitive-a-02498383-01"}],
  "ewn-abundant-a-00013906-01" : [{"relType":"pertainym","synset":"ewn-00215852-r","sense":"ewn-abundantly-r-00215852-01"},{"relType":"derivation","synset":"ewn-02721154-v","sense":"ewn-abound-v-02721154-01"},{"relType":"derivation","synset":"ewn-05122340-n","sense":"ewn-abundance-n-05122340-01"},{"relType":"antonym","synset":"ewn-00016794-a","sense":"ewn-scarce-a-00016794-01"}],
  "ewn-promiser-n-10501639-01" : [{"relType":"derivation","synset":"ewn-00885532-v","sense":"ewn-promise-v-00885532-01"}],
  "ewn-satisfactory-s-01128566-01" : [{"relType":"derivation","synset":"ewn-02677669-v","sense":"ewn-satisfy-v-02677669-01"},{"relType":"derivation","synset":"ewn-01185870-v","sense":"ewn-satisfy-v-01185870-04"},{"relType":"derivation","synset":"ewn-04799358-n","sense":"ewn-satisfactoriness-n-04799358-01"}],
  "ewn-reference-n-05931946-01" : [{"relType":"derivation","synset":"ewn-00657226-v","sense":"ewn-refer-v-00657226-01"},{"relType":"derivation","synset":"ewn-00933429-v","sense":"ewn-refer-v-00933429-02"},{"relType":"derivation","synset":"ewn-00726459-s","sense":"ewn-referential-s-00726459-01"}],
  "ewn-origin-n-07338522-01" : [{"relType":"derivation","synset":"ewn-02630344-v","sense":"ewn-originate-v-02630344-01"},{"relType":"derivation","synset":"ewn-01631641-v","sense":"ewn-originate-v-01631641-01"},{"relType":"derivation","synset":"ewn-02749218-v","sense":"ewn-originate-v-02749218-01"},{"relType":"pertainym","synset":"ewn-02745127-a","sense":"ewn-genetic-a-02745127-01"}],
  "ewn-emergence-n-07334509-01" : [{"relType":"derivation","synset":"ewn-00424924-v","sense":"ewn-emerge-v-00424924-01"}],
  "ewn-counter-n-09989021-01" : [{"relType":"derivation","synset":"ewn-00950103-v","sense":"ewn-count-v-00950103-01"}],
  "ewn-spread_out-v-02064069-03" : [{"relType":"also","synset":"ewn-01381221-v","sense":"ewn-spread-v-01381221-01"},{"relType":"also","synset":"ewn-01381221-v","sense":"ewn-spread-v-01381221-01"}],
  "ewn-easy_money-n-13277202-01" : [{"relType":"antonym","synset":"ewn-13277333-n","sense":"ewn-tight_money-n-13277333-01"}],
  "ewn-federalize-v-00505545-01" : [{"relType":"derivation","synset":"ewn-14442374-n","sense":"ewn-federalization-n-14442374-01"},{"relType":"derivation","synset":"ewn-00806040-n","sense":"ewn-federalization-n-00806040-01"}],
  "ewn-null-s-02510539-01" : [{"relType":"derivation","synset":"ewn-06544754-n","sense":"ewn-nullity-n-06544754-01"}],
  "ewn-flap-v-02097888-02" : [{"relType":"derivation","synset":"ewn-07453884-n","sense":"ewn-flap-n-07453884-01"},{"relType":"derivation","synset":"ewn-07453884-n","sense":"ewn-flapping-n-07453884-02"}],
  "ewn-striking-s-00583156-05" : [{"relType":"derivation","synset":"ewn-14457488-n","sense":"ewn-strikingness-n-14457488-03"}],
  "ewn-disable-v-00091720-01" : [{"relType":"derivation","synset":"ewn-14571935-n","sense":"ewn-disablement-n-14571935-02"}],
  "ewn-lightless-s-00276851-01" : [{"relType":"derivation","synset":"ewn-14007292-n","sense":"ewn-lightlessness-n-14007292-02"}],
  "ewn-wobble-v-01872996-01" : [{"relType":"derivation","synset":"ewn-04603957-n","sense":"ewn-wobbler-n-04603957-01"},{"relType":"derivation","synset":"ewn-07379300-n","sense":"ewn-wobble-n-07379300-01"}],
  "ewn-sketch-v-01701523-01" : [{"relType":"derivation","synset":"ewn-10624288-n","sense":"ewn-sketcher-n-10624288-01"},{"relType":"derivation","synset":"ewn-04234581-n","sense":"ewn-sketcher-n-04234581-01"},{"relType":"derivation","synset":"ewn-04234206-n","sense":"ewn-sketch-n-04234206-01"}],
  "ewn-drill-v-00607488-01" : [{"relType":"derivation","synset":"ewn-00896250-n","sense":"ewn-drill-n-00896250-03"}],
  "ewn-cannoneer-n-09831257-02" : [{"relType":"derivation","synset":"ewn-02953692-n","sense":"ewn-cannon-n-02953692-01"},{"relType":"derivation","synset":"ewn-02954262-n","sense":"ewn-cannon-n-02954262-01"},{"relType":"derivation","synset":"ewn-02953918-n","sense":"ewn-cannon-n-02953918-01"},{"relType":"derivation","synset":"ewn-01136948-v","sense":"ewn-cannon-v-01136948-01"}],
  "ewn-brace-v-01222270-01" : [{"relType":"derivation","synset":"ewn-02889840-n","sense":"ewn-bracing-n-02889840-02"},{"relType":"derivation","synset":"ewn-02890450-n","sense":"ewn-brace-n-02890450-01"},{"relType":"derivation","synset":"ewn-02889840-n","sense":"ewn-brace-n-02889840-01"}],
  "ewn-chain-v-01291239-01" : [{"relType":"derivation","synset":"ewn-03003017-n","sense":"ewn-chain-n-03003017-01"},{"relType":"antonym","synset":"ewn-01291411-v","sense":"ewn-unchain-v-01291411-01"}],
  "ewn-steer-v-01935739-01" : [{"relType":"derivation","synset":"ewn-00816834-n","sense":"ewn-steerage-n-00816834-02"},{"relType":"derivation","synset":"ewn-10189389-n","sense":"ewn-steerer-n-10189389-03"},{"relType":"derivation","synset":"ewn-01147389-n","sense":"ewn-steering-n-01147389-02"},{"relType":"derivation","synset":"ewn-00816834-n","sense":"ewn-steering-n-00816834-01"}],
  "ewn-picket-v-01291629-01" : [{"relType":"derivation","synset":"ewn-03936190-n","sense":"ewn-picket-n-03936190-01"}],
  "ewn-damp-v-00574162-01" : [{"relType":"derivation","synset":"ewn-01148418-n","sense":"ewn-damper-n-01148418-01"}],
  "ewn-tubeless-a-02476222-01" : [{"relType":"derivation","synset":"ewn-04502057-n","sense":"ewn-tubeless-n-04502057-01"},{"relType":"antonym","synset":"ewn-02476139-a","sense":"ewn-tubed-a-02476139-01"}],
  "ewn-scrape-v-01753964-01" : [{"relType":"derivation","synset":"ewn-04158045-n","sense":"ewn-scraper-n-04158045-01"}],
  "ewn-mecopterous-a-02770783-01" : [{"relType":"derivation","synset":"ewn-02164596-n","sense":"ewn-Mecoptera-n-02164596-01"}],
  "ewn-reprobation-n-14437550-01" : [{"relType":"derivation","synset":"ewn-01073177-v","sense":"ewn-reprobate-v-01073177-01"}],
  "ewn-cantillation-n-01257469-01" : [{"relType":"derivation","synset":"ewn-01051609-v","sense":"ewn-cantillate-v-01051609-04"}],
  "ewn-click-n-00113648-01" : [{"relType":"derivation","synset":"ewn-01897764-v","sense":"ewn-click-v-01897764-02"}],
  "ewn-convict-n-09982638-01" : [{"relType":"derivation","synset":"ewn-00908320-v","sense":"ewn-convict-v-00908320-01"}],
  "ewn-approbatory-s-00999508-04" : [{"relType":"derivation","synset":"ewn-00675902-v","sense":"ewn-approve-v-00675902-01"}],
  "ewn-advisee-n-09793590-01" : [{"relType":"derivation","synset":"ewn-00874568-v","sense":"ewn-advise-v-00874568-02"}],
  "ewn-iterative-s-01971457-01" : [{"relType":"derivation","synset":"ewn-00960366-v","sense":"ewn-iterate-v-00960366-04"},{"relType":"derivation","synset":"ewn-00344254-v","sense":"ewn-iterate-v-00344254-01"}],
  "ewn-prompter-n-04017155-01" : [{"relType":"derivation","synset":"ewn-00879379-v","sense":"ewn-prompt-v-00879379-01"}],
  "ewn-spit-n-00119372-01" : [{"relType":"derivation","synset":"ewn-00101710-v","sense":"ewn-spit-v-00101710-01"}],
  "ewn-concurrence-n-05055452-01" : [{"relType":"derivation","synset":"ewn-00345966-v","sense":"ewn-concur-v-00345966-01"},{"relType":"derivation","synset":"ewn-02387064-s","sense":"ewn-concurrent-s-02387064-04"}],
  "ewn-compromise-n-01208054-01" : [{"relType":"derivation","synset":"ewn-01037675-v","sense":"ewn-compromise-v-01037675-01"},{"relType":"derivation","synset":"ewn-01037252-v","sense":"ewn-compromise-v-01037252-01"}],
  "ewn-expounding-n-06755121-02" : [{"relType":"derivation","synset":"ewn-00957633-v","sense":"ewn-expound-v-00957633-08"}],
  "ewn-contester-n-09635321-01" : [{"relType":"derivation","synset":"ewn-00871260-v","sense":"ewn-contest-v-00871260-01"}],
  "ewn-vindicator-n-09817975-02" : [{"relType":"derivation","synset":"ewn-00897737-v","sense":"ewn-vindicate-v-00897737-02"},{"relType":"derivation","synset":"ewn-00906643-v","sense":"ewn-vindicate-v-00906643-01"}],
  "ewn-admonitory-s-01000283-01" : [{"relType":"derivation","synset":"ewn-00825727-v","sense":"ewn-admonish-v-00825727-01"}],
  "ewn-mount-n-03798059-01" : [{"relType":"derivation","synset":"ewn-00408558-v","sense":"ewn-mount-v-00408558-01"}],
  "ewn-twiddle-n-00341815-01" : [{"relType":"derivation","synset":"ewn-02052840-v","sense":"ewn-twiddle-v-02052840-03"}],
  "ewn-skim_off-v-00679364-02" : [{"relType":"also","synset":"ewn-01263582-v","sense":"ewn-skim-v-01263582-01"},{"relType":"also","synset":"ewn-01263582-v","sense":"ewn-skim-v-01263582-01"}],
  "ewn-hop_out-v-01927685-01" : [{"relType":"antonym","synset":"ewn-01927367-v","sense":"ewn-hop_on-v-01927367-01"}],
  "ewn-rally-v-00529688-01" : [{"relType":"derivation","synset":"ewn-13567048-n","sense":"ewn-rally-n-13567048-01"}],
  "ewn-Iberian-a-02970260-01" : [{"relType":"derivation","synset":"ewn-09006937-n","sense":"ewn-Iberia-n-09006937-02"}],
  "ewn-interrelate-v-00715723-01" : [{"relType":"derivation","synset":"ewn-13866409-n","sense":"ewn-interrelation-n-13866409-01"}],
  "ewn-vaporous-s-00464579-03" : [{"relType":"derivation","synset":"ewn-15080200-n","sense":"ewn-vapor-n-15080200-01"}],
  "ewn-aphanitic-a-02642914-01" : [{"relType":"derivation","synset":"ewn-14750494-n","sense":"ewn-aphanite-n-14750494-01"}],
  "ewn-brecciate-v-01587942-01" : [{"relType":"derivation","synset":"ewn-14722000-n","sense":"ewn-breccia-n-14722000-01"}],
  "ewn-fisher-n-10113427-02" : [{"relType":"derivation","synset":"ewn-01143220-v","sense":"ewn-fish-v-01143220-01"}],
  "ewn-scourer-n-10582073-01" : [{"relType":"derivation","synset":"ewn-01253792-v","sense":"ewn-scour-v-01253792-02"}],
  "ewn-beeswax-n-15119391-01" : [{"relType":"derivation","synset":"ewn-01271434-v","sense":"ewn-beeswax-v-01271434-01"}],
  "ewn-dent-n-13927849-05" : [{"relType":"derivation","synset":"ewn-01282234-v","sense":"ewn-dent-v-01282234-02"}],
  "ewn-grasping-n-05814863-01" : [{"relType":"derivation","synset":"ewn-00589616-v","sense":"ewn-grasp-v-00589616-06"}],
  "ewn-octosyllabic-s-02296883-01" : [{"relType":"derivation","synset":"ewn-07111091-n","sense":"ewn-octosyllable-n-07111091-01"}],
  "ewn-nonintervention-n-06674492-01" : [{"relType":"antonym","synset":"ewn-06674307-n","sense":"ewn-intervention-n-06674307-01"}],
  "ewn-holler-v-00915018-07" : [{"relType":"derivation","synset":"ewn-07136069-n","sense":"ewn-hollering-n-07136069-05"},{"relType":"derivation","synset":"ewn-07136069-n","sense":"ewn-holler-n-07136069-04"}],
  "ewn-comment-v-01035061-01" : [{"relType":"derivation","synset":"ewn-06775422-n","sense":"ewn-comment-n-06775422-01"}],
  "ewn-Loxitane-n-03699816-02" : [{"relType":"is_exemplified_by","synset":"ewn-06858649-n","sense":"ewn-trade_name-n-06858649-01"}],
  "ewn-pamphleteer-n-10415304-01" : [{"relType":"derivation","synset":"ewn-06425532-n","sense":"ewn-pamphlet-n-06425532-05"},{"relType":"derivation","synset":"ewn-06420933-n","sense":"ewn-pamphlet-n-06420933-02"}],
  "ewn-wholesome-s-01176236-01" : [{"relType":"derivation","synset":"ewn-04796917-n","sense":"ewn-wholesomeness-n-04796917-01"}],
  "ewn-tasteless-a-02408123-01" : [{"relType":"derivation","synset":"ewn-05004197-n","sense":"ewn-tastelessness-n-05004197-05"},{"relType":"antonym","synset":"ewn-02403682-a","sense":"ewn-tasty-a-02403682-01"}],
  "ewn-tolerate-v-02463017-01" : [{"relType":"derivation","synset":"ewn-01144645-n","sense":"ewn-toleration-n-01144645-01"},{"relType":"derivation","synset":"ewn-02445545-a","sense":"ewn-tolerant-a-02445545-01"},{"relType":"derivation","synset":"ewn-00287703-s","sense":"ewn-tolerant-s-00287703-04"}],
  "ewn-hike-v-01924925-01" : [{"relType":"derivation","synset":"ewn-00289814-n","sense":"ewn-hike-n-00289814-01"},{"relType":"derivation","synset":"ewn-10195742-n","sense":"ewn-hiker-n-10195742-01"}],
  "ewn-help-v-00081834-01" : [{"relType":"derivation","synset":"ewn-01210099-n","sense":"ewn-help-n-01210099-04"},{"relType":"derivation","synset":"ewn-05162155-n","sense":"ewn-help-n-05162155-03"}],
  "ewn-charitable-a-02702127-01" : [{"relType":"derivation","synset":"ewn-04839281-n","sense":"ewn-charitableness-n-04839281-01"}],
  "ewn-essential-s-01584714-01" : [{"relType":"derivation","synset":"ewn-05178572-n","sense":"ewn-essentialness-n-05178572-02"},{"relType":"derivation","synset":"ewn-09390100-n","sense":"ewn-essential-n-09390100-02"}],
  "ewn-open-s-01313228-02" : [{"relType":"derivation","synset":"ewn-04661423-n","sense":"ewn-openness-n-04661423-01"}],
  "ewn-elaborate-s-00311231-02" : [{"relType":"derivation","synset":"ewn-04774107-n","sense":"ewn-elaborateness-n-04774107-01"}],
  "ewn-flake-v-01262515-04" : [{"relType":"derivation","synset":"ewn-09244958-n","sense":"ewn-flake-n-09244958-03"}],
  "ewn-gun-n-00124250-01" : [{"relType":"derivation","synset":"ewn-01139040-v","sense":"ewn-gun-v-01139040-01"}],
  "ewn-Anglican-a-02966005-01" : [{"relType":"derivation","synset":"ewn-09977771-n","sense":"ewn-Anglican-n-09977771-01"}],
  "ewn-succour-v-02554407-02" : [{"relType":"derivation","synset":"ewn-10691337-n","sense":"ewn-succourer-n-10691337-02"},{"relType":"derivation","synset":"ewn-01211710-n","sense":"ewn-succour-n-01211710-03"}],
  "ewn-meddle-v-02544767-01" : [{"relType":"derivation","synset":"ewn-10324859-n","sense":"ewn-meddler-n-10324859-01"},{"relType":"derivation","synset":"ewn-00202365-n","sense":"ewn-meddling-n-00202365-01"}],
  "ewn-periodontics-n-06058382-01" : [{"relType":"derivation","synset":"ewn-10436312-n","sense":"ewn-periodontist-n-10436312-01"},{"relType":"derivation","synset":"ewn-02927319-a","sense":"ewn-periodontal-a-02927319-02"},{"relType":"pertainym","synset":"ewn-02927319-a","sense":"ewn-periodontal-a-02927319-02"},{"relType":"derivation","synset":"ewn-02927319-a","sense":"ewn-periodontic-a-02927319-01"},{"relType":"pertainym","synset":"ewn-02927319-a","sense":"ewn-periodontic-a-02927319-01"}],
  "ewn-planetal-a-02789475-01" : [{"relType":"derivation","synset":"ewn-09416900-n","sense":"ewn-planet-n-09416900-01"},{"relType":"derivation","synset":"ewn-09417539-n","sense":"ewn-planet-n-09417539-01"}],
  "ewn-extrovert-n-10094629-01" : [{"relType":"antonym","synset":"ewn-10233099-n","sense":"ewn-introvert-n-10233099-01"}],
  "ewn-industry-n-08082070-01" : [{"relType":"derivation","synset":"ewn-10223796-n","sense":"ewn-industrialist-n-10223796-01"}],
  "ewn-reproach-v-00827636-01" : [{"relType":"derivation","synset":"ewn-10759674-n","sense":"ewn-reproacher-n-10759674-03"}],
  "ewn-father-v-00054345-04" : [{"relType":"derivation","synset":"ewn-10100638-n","sense":"ewn-father-n-10100638-01"}],
  "ewn-stint-v-02230521-01" : [{"relType":"derivation","synset":"ewn-10676271-n","sense":"ewn-stinter-n-10676271-01"}],
  "ewn-recusant-s-01695755-02" : [{"relType":"derivation","synset":"ewn-09977313-n","sense":"ewn-recusant-n-09977313-02"},{"relType":"derivation","synset":"ewn-01246000-n","sense":"ewn-recusancy-n-01246000-01"}],
  "ewn-cosmogony-n-06107802-02" : [{"relType":"derivation","synset":"ewn-02714174-a","sense":"ewn-cosmogonical-a-02714174-04"},{"relType":"pertainym","synset":"ewn-02714174-a","sense":"ewn-cosmogonical-a-02714174-04"},{"relType":"derivation","synset":"ewn-02714174-a","sense":"ewn-cosmogonic-a-02714174-03"},{"relType":"pertainym","synset":"ewn-02714174-a","sense":"ewn-cosmogonic-a-02714174-03"}],
  "ewn-trauma-n-14309164-04" : [{"relType":"derivation","synset":"ewn-02956209-a","sense":"ewn-traumatic-a-02956209-01"},{"relType":"pertainym","synset":"ewn-02956209-a","sense":"ewn-traumatic-a-02956209-01"},{"relType":"derivation","synset":"ewn-00089938-v","sense":"ewn-traumatize-v-00089938-01"},{"relType":"derivation","synset":"ewn-00089938-v","sense":"ewn-traumatise-v-00089938-02"}],
  "ewn-satyr-n-10572408-01" : [{"relType":"derivation","synset":"ewn-03125549-a","sense":"ewn-satyrical-a-03125549-02"},{"relType":"derivation","synset":"ewn-03125549-a","sense":"ewn-satyric-a-03125549-01"}],
  "ewn-Panamanian-n-09745534-01" : [{"relType":"derivation","synset":"ewn-02978027-a","sense":"ewn-Panamanian-a-02978027-01"}],
  "ewn-dysplasia-n-14389355-01" : [{"relType":"derivation","synset":"ewn-02726303-a","sense":"ewn-dysplastic-a-02726303-01"},{"relType":"pertainym","synset":"ewn-02726303-a","sense":"ewn-dysplastic-a-02726303-01"}],
  "ewn-Gaul-n-08949495-01" : [{"relType":"pertainym","synset":"ewn-03078406-a","sense":"ewn-Gallic-a-03078406-01"}],
  "ewn-Edward-n-10971451-01" : [{"relType":"derivation","synset":"ewn-03074395-a","sense":"ewn-Edwardian-a-03074395-01"}],
  "ewn-Colombia-n-08749949-01" : [{"relType":"derivation","synset":"ewn-02979163-a","sense":"ewn-Colombian-a-02979163-01"},{"relType":"pertainym","synset":"ewn-02979163-a","sense":"ewn-Colombian-a-02979163-01"}],
  "ewn-thermion-n-09480329-01" : [{"relType":"derivation","synset":"ewn-03136454-a","sense":"ewn-thermionic-a-03136454-01"},{"relType":"pertainym","synset":"ewn-03136454-a","sense":"ewn-thermionic-a-03136454-01"}],
  "ewn-Carnot_cycle-n-07356265-01" : [{"relType":"pertainym","synset":"ewn-02718968-a","sense":"ewn-cyclic-a-02718968-01"}],
  "ewn-ear-n-05328447-01" : [{"relType":"pertainym","synset":"ewn-02659552-a","sense":"ewn-aural-a-02659552-01"},{"relType":"pertainym","synset":"ewn-02990573-a","sense":"ewn-otic-a-02990573-01"}],
  "ewn-Glasgow-n-08913198-01" : [{"relType":"derivation","synset":"ewn-02982856-a","sense":"ewn-Glaswegian-a-02982856-01"},{"relType":"pertainym","synset":"ewn-02982856-a","sense":"ewn-Glaswegian-a-02982856-01"}],
  "ewn-sepsis-n-14204330-01" : [{"relType":"derivation","synset":"ewn-02121107-a","sense":"ewn-septic-a-02121107-01"},{"relType":"derivation","synset":"ewn-03010177-a","sense":"ewn-septic-a-03010177-01"}],
  "ewn-propulsion-n-11518177-01" : [{"relType":"pertainym","synset":"ewn-03115497-a","sense":"ewn-propulsive-a-03115497-01"}],
  "ewn-domicile-n-08576692-01" : [{"relType":"derivation","synset":"ewn-03073685-a","sense":"ewn-domiciliary-a-03073685-01"}],
  "ewn-subfamily_Anserinae-n-01860664-02" : [{"relType":"pertainym","synset":"ewn-02638490-a","sense":"ewn-anserine-a-02638490-01"}],
  "ewn-hopefulness-n-07556704-01" : [{"relType":"antonym","synset":"ewn-07557637-n","sense":"ewn-hopelessness-n-07557637-01"},{"relType":"derivation","synset":"ewn-01231403-a","sense":"ewn-hopeful-a-01231403-01"}],
  "ewn-refinement-n-14483408-02" : [{"relType":"derivation","synset":"ewn-00474948-v","sense":"ewn-refine-v-00474948-02"}],
  "ewn-enervation-n-05049025-01" : [{"relType":"derivation","synset":"ewn-00390527-v","sense":"ewn-enervate-v-00390527-01"}],
  "ewn-tumefaction-n-13591777-01" : [{"relType":"derivation","synset":"ewn-00258723-v","sense":"ewn-tumefy-v-00258723-01"},{"relType":"derivation","synset":"ewn-00257393-v","sense":"ewn-tumefy-v-00257393-04"}],
  "ewn-luxury-n-14515957-01" : [{"relType":"derivation","synset":"ewn-01207423-v","sense":"ewn-luxuriate-v-01207423-01"},{"relType":"derivation","synset":"ewn-01194178-v","sense":"ewn-luxuriate-v-01194178-02"},{"relType":"derivation","synset":"ewn-02032205-s","sense":"ewn-luxurious-s-02032205-04"}],
  "ewn-maceration-n-05009032-05" : [{"relType":"derivation","synset":"ewn-00390077-v","sense":"ewn-macerate-v-00390077-03"}],
  "ewn-materialization-n-13533239-01" : [{"relType":"derivation","synset":"ewn-00344828-v","sense":"ewn-materialize-v-00344828-02"}],
  "ewn-revaluation-n-05755527-02" : [{"relType":"derivation","synset":"ewn-00316996-v","sense":"ewn-revalue-v-00316996-04"},{"relType":"derivation","synset":"ewn-00316611-v","sense":"ewn-revalue-v-00316611-01"}],
  "ewn-contamination-n-14846154-02" : [{"relType":"derivation","synset":"ewn-00493642-v","sense":"ewn-contaminate-v-00493642-03"},{"relType":"derivation","synset":"ewn-00494195-v","sense":"ewn-contaminate-v-00494195-01"}],
  "ewn-think_up-v-01637684-01" : [{"relType":"also","synset":"ewn-00630153-v","sense":"ewn-think-v-00630153-01"},{"relType":"also","synset":"ewn-00630153-v","sense":"ewn-think-v-00630153-01"}],
  "ewn-odorless-a-01061474-01" : [{"relType":"antonym","synset":"ewn-01058772-a","sense":"ewn-odorous-a-01058772-01"}],
  "ewn-unscholarly-a-02091684-01" : [{"relType":"antonym","synset":"ewn-02090761-a","sense":"ewn-scholarly-a-02090761-01"}],
  "ewn-eccrine-a-00099589-01" : [{"relType":"antonym","synset":"ewn-00099382-a","sense":"ewn-apocrine-a-00099382-01"}],
  "ewn-nasality-n-04996598-01" : [{"relType":"derivation","synset":"ewn-01216222-s","sense":"ewn-nasal-s-01216222-03"}],
  "ewn-stuntedness-n-05114795-03" : [{"relType":"derivation","synset":"ewn-02356454-s","sense":"ewn-stunted-s-02356454-03"}],
  "ewn-inclementness-n-14546692-03" : [{"relType":"derivation","synset":"ewn-00440307-a","sense":"ewn-inclement-a-00440307-01"}],
  "ewn-deliquesce-v-00554130-01" : [{"relType":"derivation","synset":"ewn-00494202-s","sense":"ewn-deliquescent-s-00494202-01"}],
  "ewn-positive-a-01825607-01" : [{"relType":"antonym","synset":"ewn-01825842-a","sense":"ewn-negative-a-01825842-01"}],
  "ewn-antique-n-10396589-05" : [{"relType":"derivation","synset":"ewn-01643104-s","sense":"ewn-antique-s-01643104-02"}],
  "ewn-numbness-n-04643967-03" : [{"relType":"derivation","synset":"ewn-02114666-s","sense":"ewn-numb-p-s-02114666-02"}],
  "ewn-frankness-n-04878915-04" : [{"relType":"derivation","synset":"ewn-00768027-s","sense":"ewn-frank-s-00768027-04"}],
  "ewn-dextral-a-00746491-01" : [{"relType":"antonym","synset":"ewn-00747047-a","sense":"ewn-sinistral-a-00747047-01"}],
  "ewn-plausibleness-n-04790988-02" : [{"relType":"derivation","synset":"ewn-01803966-a","sense":"ewn-plausible-a-01803966-01"}],
  "ewn-dinge-n-14522151-02" : [{"relType":"derivation","synset":"ewn-00422169-s","sense":"ewn-dingy-s-00422169-02"},{"relType":"derivation","synset":"ewn-01915458-s","sense":"ewn-dingy-s-01915458-02"}],
  "ewn-convenience-n-14469959-01" : [{"relType":"derivation","synset":"ewn-00607261-a","sense":"ewn-convenient-a-00607261-01"}],
  "ewn-informality-n-04794222-02" : [{"relType":"derivation","synset":"ewn-01047939-a","sense":"ewn-informal-a-01047939-01"}],
  "ewn-overindulgence-n-01075579-01" : [{"relType":"derivation","synset":"ewn-01302333-s","sense":"ewn-overindulgent-s-01302333-01"},{"relType":"derivation","synset":"ewn-01195632-v","sense":"ewn-overindulge-v-01195632-03"}],
  "ewn-dough-n-07876964-01" : [{"relType":"derivation","synset":"ewn-01188960-s","sense":"ewn-doughy-s-01188960-01"}],
  "ewn-conifer-n-13129600-01" : [{"relType":"derivation","synset":"ewn-00916834-s","sense":"ewn-coniferous-s-00916834-01"}],
  "ewn-collateral-a-01420079-01" : [{"relType":"antonym","synset":"ewn-01419359-a","sense":"ewn-lineal-a-01419359-01"}],
  "ewn-postmeridian-a-00131668-01" : [{"relType":"antonym","synset":"ewn-00131484-a","sense":"ewn-antemeridian-a-00131484-01"}],
  "ewn-effectuality-n-05206554-04" : [{"relType":"derivation","synset":"ewn-00837737-a","sense":"ewn-effectual-a-00837737-02"}],
  "ewn-hostilities-n-00966892-01" : [{"relType":"derivation","synset":"ewn-01081517-a","sense":"ewn-hostile-a-01081517-01"}],
  "ewn-malfunctioning-a-01095835-01" : [{"relType":"antonym","synset":"ewn-01095249-a","sense":"ewn-functioning-a-01095249-01"}],
  "ewn-disenfranchised-a-00880044-01" : [{"relType":"antonym","synset":"ewn-00879918-a","sense":"ewn-enfranchised-a-00879918-01"}],
  "ewn-owned-a-00361386-01" : [{"relType":"antonym","synset":"ewn-00361649-a","sense":"ewn-unowned-a-00361649-01"}],
  "ewn-timorousness-n-07537968-03" : [{"relType":"derivation","synset":"ewn-00253364-s","sense":"ewn-timorous-s-00253364-02"},{"relType":"derivation","synset":"ewn-00253364-s","sense":"ewn-timorous-s-00253364-02"},{"relType":"derivation","synset":"ewn-00266855-s","sense":"ewn-timid-s-00266855-03"}],
  "ewn-morbidity-n-05707871-01" : [{"relType":"derivation","synset":"ewn-02570592-s","sense":"ewn-morbid-s-02570592-01"}],
  "ewn-following-a-00201161-01" : [{"relType":"antonym","synset":"ewn-00200496-a","sense":"ewn-leading-a-00200496-01"}],
  "ewn-unguided-a-01432232-01" : [{"relType":"antonym","synset":"ewn-01431845-a","sense":"ewn-guided-a-01431845-01"}],
  "ewn-nonspeaking-a-00154507-01" : [{"relType":"antonym","synset":"ewn-00154164-a","sense":"ewn-speaking-a-a-00154164-01"}],
  "ewn-torture-n-07510691-03" : [{"relType":"derivation","synset":"ewn-01716177-s","sense":"ewn-torturous-s-01716177-06"},{"relType":"derivation","synset":"ewn-01806671-v","sense":"ewn-torture-v-01806671-02"}],
  "ewn-doggedness-n-04871746-01" : [{"relType":"derivation","synset":"ewn-02335561-s","sense":"ewn-dogged-s-02335561-01"}],
  "ewn-undiluted-a-00760249-01" : [{"relType":"antonym","synset":"ewn-00759612-a","sense":"ewn-diluted-a-00759612-01"}],
  "ewn-overflow-v-02076087-01" : [{"relType":"derivation","synset":"ewn-00330645-n","sense":"ewn-overflow-n-00330645-02"},{"relType":"derivation","synset":"ewn-07421872-n","sense":"ewn-overflow-n-07421872-01"}],
  "ewn-defervesce-v-00572978-01" : [{"relType":"derivation","synset":"ewn-07383082-n","sense":"ewn-defervescence-n-07383082-01"}],
  "ewn-abashment-n-07523331-01" : [{"relType":"derivation","synset":"ewn-01796126-v","sense":"ewn-abash-v-01796126-02"}],
  "ewn-distraction-n-05692245-01" : [{"relType":"derivation","synset":"ewn-01768023-v","sense":"ewn-distract-v-01768023-06"}],
  "ewn-despair-n-14509858-01" : [{"relType":"derivation","synset":"ewn-01814900-v","sense":"ewn-despair-v-01814900-01"}],
  "ewn-confection-v-01629457-02" : [{"relType":"derivation","synset":"ewn-00928483-n","sense":"ewn-confection-n-00928483-01"}],
  "ewn-doodle-n-04162371-03" : [{"relType":"derivation","synset":"ewn-01697219-v","sense":"ewn-doodle-v-01697219-01"}],
  "ewn-volley-v-01077891-01" : [{"relType":"derivation","synset":"ewn-00570770-n","sense":"ewn-volley-n-00570770-01"}],
  "ewn-insurgent-s-00966472-01" : [{"relType":"derivation","synset":"ewn-00965352-n","sense":"ewn-insurgency-n-00965352-01"}],
  "ewn-dangle-v-01484915-01" : [{"relType":"derivation","synset":"ewn-01019643-n","sense":"ewn-dangling-n-01019643-02"}],
  "ewn-cobble-v-00262731-01" : [{"relType":"derivation","synset":"ewn-00619105-n","sense":"ewn-cobbling-n-00619105-03"}],
  "ewn-remove-v-02228837-02" : [{"relType":"derivation","synset":"ewn-00392407-n","sense":"ewn-removal-n-00392407-01"}],
  "ewn-decamp-v-02077642-04" : [{"relType":"derivation","synset":"ewn-00056453-n","sense":"ewn-decampment-n-00056453-02"}],
  "ewn-rebury-v-02462283-01" : [{"relType":"derivation","synset":"ewn-01052687-n","sense":"ewn-reburial-n-01052687-02"}],
  "ewn-mismanage-v-02443726-01" : [{"relType":"derivation","synset":"ewn-01136800-n","sense":"ewn-mismanagement-n-01136800-01"}],
  "ewn-musing-n-05793513-05" : [{"relType":"derivation","synset":"ewn-00632042-v","sense":"ewn-muse-v-00632042-07"}],
  "ewn-keep_track-v-00596529-01" : [{"relType":"antonym","synset":"ewn-00596701-v","sense":"ewn-lose_track-v-00596701-01"}],
  "ewn-copyreader-n-09984189-02" : [{"relType":"derivation","synset":"ewn-00629787-v","sense":"ewn-copyread-v-00629787-01"}],
  "ewn-crick-n-14384587-01" : [{"relType":"derivation","synset":"ewn-00025503-v","sense":"ewn-crick-v-00025503-01"}],
  "ewn-laugh_off-v-00803798-01" : [{"relType":"also","synset":"ewn-00031813-v","sense":"ewn-laugh-v-00031813-01"},{"relType":"also","synset":"ewn-00031813-v","sense":"ewn-laugh-v-00031813-01"}],
  "ewn-sedimentary-a-02963446-01" : [{"relType":"derivation","synset":"ewn-09451871-n","sense":"ewn-sediment-n-09451871-01"}]
}